Workbook

Sheet Assumptions
B1: 12-Month Rolling Budget
B3: Standard Cost Assumptions
B4: Per product | C4: Alpha | D4: Beta | E4: Gamma
B5: Budget sales volume (units p.a.) | C5: 120000 | D5: 72000 | E5: 45000
B6: Budget selling price (₹ / unit) | C6: 850 | D6: 1250 | E6: 2100
B7: Standard direct material (₹ / unit) | C7: 320 | D7: 480 | E7: 820
B8: Standard labour hours per unit | C8: 0.5 | D8: 0.8 | E8: 1.2
B9: Standard labour rate (₹ / hour) | C9: 260 | D9: 280 | E9: 300
B10: Standard direct labour cost (₹ / unit) | C10: =C8*C9 -> 130 | D10: =D8*D9 -> 224 | E10: =E8*E9 -> 360
B11: Standard variable overhead (₹ / unit) | C11: =$C8*$C$32 -> 60 | D11: =D8*$C$32 -> 96 | E11: =E8*$C$32 -> 144
B12: Standard variable cost (₹ / unit) | C12: =C7+C10+C11 -> 510 | D12: =D7+D10+D11 -> 800 | E12: =E7+E10+E11 -> 1324
B13: Standard contribution (₹ / unit) | C13: =C6-C12 -> 340 | D13: =D6-D12 -> 450 | E13: =E6-E12 -> 776
B14: Standard fixed OH absorbed (₹ / unit) | C14: =C8*$C$31 -> 227.27273 | D14: =D8*$C$31 -> 363.63636 | E14: =E8*$C$31 -> 545.45455
B15: Budget sales mix % | C15: =C5/SUM($C$5:$E$5) -> 0.50632911 | D15: =D5/SUM($C$5:$E$5) -> 0.30379747 | E15: =E5/SUM($C$5:$E$5) -> 0.18987342
B16: Budget labour hours p.a. | C16: =C5*C8 -> 60000 | D16: =D5*D8 -> 57600 | E16: =E5*E8 -> 54000
B18: Monthly Seasonality Index (must sum to 12.00)
B19: Seasonality index | C19: 0.9 | D19: 0.95 | E19: 1 | F19: 1.05 | G19: 1.1 | H19: 1.05 | I19: 0.95 | J19: 0.9 | K19: 0.95 | L19: 1.05 | M19: 1.1 | N19: 1
B20: Check- total index | C20: =SUM(C19:N19) -> 12 | D20: =IF(C20=12,"OK","Check — Value should be equal to 12") -> OK
B22: Overhead Budget By Department
B23: Department | C23: Budgeted fixed OH (₹ p.a.) | D23: Budgeted variable OH rate (₹ / labour hr)
B24: Machining | C24: 32000000 | D24: 60
B25: Assembly | C25: 21000000 | D25: 35
B26: Packing | C26: 9000000 | D26: 15
B27: Admin & Support | C27: 16000000 | D27: 10
B28: Total overheads | C28: =SUM(C24:C27) -> 78000000 | D28: =SUM(D24:D27) -> 120
B30: Total budgeted labour hours p.a. | C30: =SUM(C16:E16) -> 171600
B31: Standard fixed OH absorption rate (₹ / labour hr) | C31: =C28/C30 -> 454.54545
B32: Standard variable OH rate (₹ / labour hr) | C32: =D28 -> 120
B34: Forecast Drivers (applied to forecast months 7-12 only)
B35: Volume vs budget (%) | C35: 0.03 | D35: Applied to seasonalised budget volume
B36: Price realisation vs budget (%) | C36: 0.015 | D36: Achieved price uplift over budget price
B37: Direct material cost inflation (%) | C37: 0.04 | D37: On standard material cost per unit
B38: Labour rate inflation (%) | C38: 0.05 | D38: On standard labour rate
B39: Variable overhead rate inflation (%) | C39: 0.03 | D39: On standard variable OH rate per hour
B40: Fixed overhead inflation (%) | C40: 0.025 | D40: On budgeted monthly fixed OH by department
B41: Labour efficiency factor (actual hrs / standard hrs) | C41: 1.02 | D41: >1 = adverse efficiency
B42: Forecast material usage factor (actual / standard) | C42: 1.015 | D42: >1 = adverse usage

Sheet Rolling Budget
B1: Rolling Budget (Apr-2026 to Mar-2027)
B2: Budget = annual assumption / 12 × monthly seasonality index
B3: Month | C3: =DATE(2026,4,1) -> 46113 | D3: =EDATE(C3,1) -> 46143 | E3: =EDATE(D3,1) -> 46174 | F3: =EDATE(E3,1) -> 46204 | G3: =EDATE(F3,1) -> 46235 | H3: =EDATE(G3,1) -> 46266 | I3: =EDATE(H3,1) -> 46296 | J3: =EDATE(I3,1) -> 46327 | K3: =EDATE(J3,1) -> 46357 | ... N3: =EDATE(M3,1) -> 46447 | O3: FY Total
B4: Actual / Forecast | C4: Actual | D4: Actual | E4: Actual | F4: Actual | G4: Actual | H4: Actual | I4: Forecast | J4: Forecast | K4: Forecast | L4: Forecast | M4: Forecast | N4: Forecast
B6: Volume (units) = annual assumption / 12 × monthly seasonality index
B7: Alpha | C7: =Assumptions!$C$5/12*Assumptions!C$19 -> 9000 | D7: =Assumptions!$C$5/12*Assumptions!D$19 -> 9500 | E7: =Assumptions!$C$5/12*Assumptions!E$19 -> 10000 | F7: =Assumptions!$C$5/12*Assumptions!F$19 -> 10500 | G7: =Assumptions!$C$5/12*Assumptions!G$19 -> 11000 | H7: =Assumptions!$C$5/12*Assumptions!H$19 -> 10500 | I7: =Assumptions!$C$5/12*Assumptions!I$19 -> 9500 | J7: =Assumptions!$C$5/12*Assumptions!J$19 -> 9000 | ... N7: =Assumptions!$C$5/12*Assumptions!N$19 -> 10000 | O7: =SUM(C7:N7) -> 120000
B8: Beta | C8: =Assumptions!$D$5/12*Assumptions!C$19 -> 5400 | D8: =Assumptions!$D$5/12*Assumptions!D$19 -> 5700 | E8: =Assumptions!$D$5/12*Assumptions!E$19 -> 6000 | F8: =Assumptions!$D$5/12*Assumptions!F$19 -> 6300 | G8: =Assumptions!$D$5/12*Assumptions!G$19 -> 6600 | H8: =Assumptions!$D$5/12*Assumptions!H$19 -> 6300 | I8: =Assumptions!$D$5/12*Assumptions!I$19 -> 5700 | J8: =Assumptions!$D$5/12*Assumptions!J$19 -> 5400 | ... N8: =Assumptions!$D$5/12*Assumptions!N$19 -> 6000 | O8: =SUM(C8:N8) -> 72000
B9: Gamma | C9: =Assumptions!$E$5/12*Assumptions!C$19 -> 3375 | D9: =Assumptions!$E$5/12*Assumptions!D$19 -> 3562.5 | E9: =Assumptions!$E$5/12*Assumptions!E$19 -> 3750 | F9: =Assumptions!$E$5/12*Assumptions!F$19 -> 3937.5 | G9: =Assumptions!$E$5/12*Assumptions!G$19 -> 4125 | H9: =Assumptions!$E$5/12*Assumptions!H$19 -> 3937.5 | I9: =Assumptions!$E$5/12*Assumptions!I$19 -> 3562.5 | J9: =Assumptions!$E$5/12*Assumptions!J$19 -> 3375 | ... N9: =Assumptions!$E$5/12*Assumptions!N$19 -> 3750 | O9: =SUM(C9:N9) -> 45000
B10: Total units | C10: =SUM(C7:C9) -> 17775 | D10: =SUM(D7:D9) -> 18762.5 | E10: =SUM(E7:E9) -> 19750 | F10: =SUM(F7:F9) -> 20737.5 | G10: =SUM(G7:G9) -> 21725 | H10: =SUM(H7:H9) -> 20737.5 | I10: =SUM(I7:I9) -> 18762.5 | J10: =SUM(J7:J9) -> 17775 | ... N10: =SUM(N7:N9) -> 19750 | O10: =SUM(C10:N10) -> 237000
B12: Revenue (₹)
B13: Alpha | C13: =C7*Assumptions!$C$6 -> 7650000 | D13: =D7*Assumptions!$C$6 -> 8075000 | E13: =E7*Assumptions!$C$6 -> 8500000 | F13: =F7*Assumptions!$C$6 -> 8925000 | G13: =G7*Assumptions!$C$6 -> 9350000 | H13: =H7*Assumptions!$C$6 -> 8925000 | I13: =I7*Assumptions!$C$6 -> 8075000 | J13: =J7*Assumptions!$C$6 -> 7650000 | ... N13: =N7*Assumptions!$C$6 -> 8500000 | O13: =SUM(C13:N13) -> 102000000
B14: Beta | C14: =C8*Assumptions!$D$6 -> 6750000 | D14: =D8*Assumptions!$D$6 -> 7125000 | E14: =E8*Assumptions!$D$6 -> 7500000 | F14: =F8*Assumptions!$D$6 -> 7875000 | G14: =G8*Assumptions!$D$6 -> 8250000 | H14: =H8*Assumptions!$D$6 -> 7875000 | I14: =I8*Assumptions!$D$6 -> 7125000 | J14: =J8*Assumptions!$D$6 -> 6750000 | ... N14: =N8*Assumptions!$D$6 -> 7500000 | O14: =SUM(C14:N14) -> 90000000
B15: Gamma | C15: =C9*Assumptions!$E$6 -> 7087500 | D15: =D9*Assumptions!$E$6 -> 7481250 | E15: =E9*Assumptions!$E$6 -> 7875000 | F15: =F9*Assumptions!$E$6 -> 8268750 | G15: =G9*Assumptions!$E$6 -> 8662500 | H15: =H9*Assumptions!$E$6 -> 8268750 | I15: =I9*Assumptions!$E$6 -> 7481250 | J15: =J9*Assumptions!$E$6 -> 7087500 | ... N15: =N9*Assumptions!$E$6 -> 7875000 | O15: =SUM(C15:N15) -> 94500000
B16: Total revenue | C16: =SUM(C13:C15) -> 21487500 | D16: =SUM(D13:D15) -> 22681250 | E16: =SUM(E13:E15) -> 23875000 | F16: =SUM(F13:F15) -> 25068750 | G16: =SUM(G13:G15) -> 26262500 | H16: =SUM(H13:H15) -> 25068750 | I16: =SUM(I13:I15) -> 22681250 | J16: =SUM(J13:J15) -> 21487500 | ... N16: =SUM(N13:N15) -> 23875000 | O16: =SUM(C16:N16) -> 286500000
B18: Standard labour hours (Volume*Standard labour hours per unit) | C18: =C7*Assumptions!$C$8+C8*Assumptions!$D$8+C9*Assumptions!$E$8 -> 12870 | D18: =D7*Assumptions!$C$8+D8*Assumptions!$D$8+D9*Assumptions!$E$8 -> 13585 | E18: =E7*Assumptions!$C$8+E8*Assumptions!$D$8+E9*Assumptions!$E$8 -> 14300 | F18: =F7*Assumptions!$C$8+F8*Assumptions!$D$8+F9*Assumptions!$E$8 -> 15015 | G18: =G7*Assumptions!$C$8+G8*Assumptions!$D$8+G9*Assumptions!$E$8 -> 15730 | H18: =H7*Assumptions!$C$8+H8*Assumptions!$D$8+H9*Assumptions!$E$8 -> 15015 | I18: =I7*Assumptions!$C$8+I8*Assumptions!$D$8+I9*Assumptions!$E$8 -> 13585 | J18: =J7*Assumptions!$C$8+J8*Assumptions!$D$8+J9*Assumptions!$E$8 -> 12870 | ... N18: =N7*Assumptions!$C$8+N8*Assumptions!$D$8+N9*Assumptions!$E$8 -> 14300 | O18: =SUM(C18:N18) -> 171600
B20: Variable Costs (₹)
B21: Direct material (Volume*Standard direct material price per unit) | C21: =C7*Assumptions!$C$7+C8*Assumptions!$D$7+C9*Assumptions!$E$7 -> 8239500 | D21: =D7*Assumptions!$C$7+D8*Assumptions!$D$7+D9*Assumptions!$E$7 -> 8697250 | E21: =E7*Assumptions!$C$7+E8*Assumptions!$D$7+E9*Assumptions!$E$7 -> 9155000 | F21: =F7*Assumptions!$C$7+F8*Assumptions!$D$7+F9*Assumptions!$E$7 -> 9612750 | G21: =G7*Assumptions!$C$7+G8*Assumptions!$D$7+G9*Assumptions!$E$7 -> 10070500 | H21: =H7*Assumptions!$C$7+H8*Assumptions!$D$7+H9*Assumptions!$E$7 -> 9612750 | I21: =I7*Assumptions!$C$7+I8*Assumptions!$D$7+I9*Assumptions!$E$7 -> 8697250 | J21: =J7*Assumptions!$C$7+J8*Assumptions!$D$7+J9*Assumptions!$E$7 -> 8239500 | ... N21: =N7*Assumptions!$C$7+N8*Assumptions!$D$7+N9*Assumptions!$E$7 -> 9155000 | O21: =SUM(C21:N21) -> 109860000
B22: Direct labour (Volume*Standard direct labour cost per unit) | C22: =C7*Assumptions!$C$10+C8*Assumptions!$D$10+C9*Assumptions!$E$10 -> 3594600 | D22: =D7*Assumptions!$C$10+D8*Assumptions!$D$10+D9*Assumptions!$E$10 -> 3794300 | E22: =E7*Assumptions!$C$10+E8*Assumptions!$D$10+E9*Assumptions!$E$10 -> 3994000 | F22: =F7*Assumptions!$C$10+F8*Assumptions!$D$10+F9*Assumptions!$E$10 -> 4193700 | G22: =G7*Assumptions!$C$10+G8*Assumptions!$D$10+G9*Assumptions!$E$10 -> 4393400 | H22: =H7*Assumptions!$C$10+H8*Assumptions!$D$10+H9*Assumptions!$E$10 -> 4193700 | I22: =I7*Assumptions!$C$10+I8*Assumptions!$D$10+I9*Assumptions!$E$10 -> 3794300 | J22: =J7*Assumptions!$C$10+J8*Assumptions!$D$10+J9*Assumptions!$E$10 -> 3594600 | ... N22: =N7*Assumptions!$C$10+N8*Assumptions!$D$10+N9*Assumptions!$E$10 -> 3994000 | O22: =SUM(C22:N22) -> 47928000
B23: Variable overhead (Standard labour hours*Standard variable OH rate per hour) | C23: =C18*Assumptions!$C$32 -> 1544400 | D23: =D18*Assumptions!$C$32 -> 1630200 | E23: =E18*Assumptions!$C$32 -> 1716000 | F23: =F18*Assumptions!$C$32 -> 1801800 | G23: =G18*Assumptions!$C$32 -> 1887600 | H23: =H18*Assumptions!$C$32 -> 1801800 | I23: =I18*Assumptions!$C$32 -> 1630200 | J23: =J18*Assumptions!$C$32 -> 1544400 | ... N23: =N18*Assumptions!$C$32 -> 1716000 | O23: =SUM(C23:N23) -> 20592000
B24: Total variable cost | C24: =SUM(C21:C23) -> 13378500 | D24: =SUM(D21:D23) -> 14121750 | E24: =SUM(E21:E23) -> 14865000 | F24: =SUM(F21:F23) -> 15608250 | G24: =SUM(G21:G23) -> 16351500 | H24: =SUM(H21:H23) -> 15608250 | I24: =SUM(I21:I23) -> 14121750 | J24: =SUM(J21:J23) -> 13378500 | ... N24: =SUM(N21:N23) -> 14865000 | O24: =SUM(C24:N24) -> 178380000
B26: Contribution | C26: =C16-C24 -> 8109000 | D26: =D16-D24 -> 8559500 | E26: =E16-E24 -> 9010000 | F26: =F16-F24 -> 9460500 | G26: =G16-G24 -> 9911000 | H26: =H16-H24 -> 9460500 | I26: =I16-I24 -> 8559500 | J26: =J16-J24 -> 8109000 | ... N26: =N16-N24 -> 9010000 | O26: =SUM(C26:N26) -> 108120000
B27: Contribution margin % | C27: =IFERROR(C26/C16,0) -> 0.3773822 | D27: =IFERROR(D26/D16,0) -> 0.3773822 | E27: =IFERROR(E26/E16,0) -> 0.3773822 | F27: =IFERROR(F26/F16,0) -> 0.3773822 | G27: =IFERROR(G26/G16,0) -> 0.3773822 | H27: =IFERROR(H26/H16,0) -> 0.3773822 | I27: =IFERROR(I26/I16,0) -> 0.3773822 | J27: =IFERROR(J26/J16,0) -> 0.3773822 | ... O27: =IFERROR(O26/O16,0) -> 0.3773822
B29: Fixed Overhead By Department (₹)
B30: Machining (Budgeted fixed OH/12) | C30: =Assumptions!$C$24/12 -> 2666666.7 | D30: =Assumptions!$C$24/12 -> 2666666.7 | E30: =Assumptions!$C$24/12 -> 2666666.7 | F30: =Assumptions!$C$24/12 -> 2666666.7 | G30: =Assumptions!$C$24/12 -> 2666666.7 | H30: =Assumptions!$C$24/12 -> 2666666.7 | I30: =Assumptions!$C$24/12 -> 2666666.7 | J30: =Assumptions!$C$24/12 -> 2666666.7 | ... N30: =Assumptions!$C$24/12 -> 2666666.7 | O30: =SUM(C30:N30) -> 32000000
B31: Assembly | C31: =Assumptions!$C$25/12 -> 1750000 | D31: =Assumptions!$C$25/12 -> 1750000 | E31: =Assumptions!$C$25/12 -> 1750000 | F31: =Assumptions!$C$25/12 -> 1750000 | G31: =Assumptions!$C$25/12 -> 1750000 | H31: =Assumptions!$C$25/12 -> 1750000 | I31: =Assumptions!$C$25/12 -> 1750000 | J31: =Assumptions!$C$25/12 -> 1750000 | ... N31: =Assumptions!$C$25/12 -> 1750000 | O31: =SUM(C31:N31) -> 21000000
B32: Packing | C32: =Assumptions!$C$26/12 -> 750000 | D32: =Assumptions!$C$26/12 -> 750000 | E32: =Assumptions!$C$26/12 -> 750000 | F32: =Assumptions!$C$26/12 -> 750000 | G32: =Assumptions!$C$26/12 -> 750000 | H32: =Assumptions!$C$26/12 -> 750000 | I32: =Assumptions!$C$26/12 -> 750000 | J32: =Assumptions!$C$26/12 -> 750000 | ... N32: =Assumptions!$C$26/12 -> 750000 | O32: =SUM(C32:N32) -> 9000000
B33: Admin & Support | C33: =Assumptions!$C$27/12 -> 1333333.3 | D33: =Assumptions!$C$27/12 -> 1333333.3 | E33: =Assumptions!$C$27/12 -> 1333333.3 | F33: =Assumptions!$C$27/12 -> 1333333.3 | G33: =Assumptions!$C$27/12 -> 1333333.3 | H33: =Assumptions!$C$27/12 -> 1333333.3 | I33: =Assumptions!$C$27/12 -> 1333333.3 | J33: =Assumptions!$C$27/12 -> 1333333.3 | ... N33: =Assumptions!$C$27/12 -> 1333333.3 | O33: =SUM(C33:N33) -> 16000000
B34: Total fixed overhead | C34: =SUM(C30:C33) -> 6500000 | D34: =SUM(D30:D33) -> 6500000 | E34: =SUM(E30:E33) -> 6500000 | F34: =SUM(F30:F33) -> 6500000 | G34: =SUM(G30:G33) -> 6500000 | H34: =SUM(H30:H33) -> 6500000 | I34: =SUM(I30:I33) -> 6500000 | J34: =SUM(J30:J33) -> 6500000 | ... N34: =SUM(N30:N33) -> 6500000 | O34: =SUM(C34:N34) -> 78000000
B36: Operating Profit | C36: =C26-C34 -> 1609000 | D36: =D26-D34 -> 2059500 | E36: =E26-E34 -> 2510000 | F36: =F26-F34 -> 2960500 | G36: =G26-G34 -> 3411000 | H36: =H26-H34 -> 2960500 | I36: =I26-I34 -> 2059500 | J36: =J26-J34 -> 1609000 | ... N36: =N26-N34 -> 2510000 | O36: =SUM(C36:N36) -> 30120000
B37: Operating margin % | C37: =IFERROR(C36/C16,0) -> 0.074880745 | D37: =IFERROR(D36/D16,0) -> 0.090801874 | E37: =IFERROR(E36/E16,0) -> 0.10513089 | F37: =IFERROR(F36/F16,0) -> 0.11809524 | G37: =IFERROR(G36/G16,0) -> 0.12988101 | H37: =IFERROR(H36/H16,0) -> 0.11809524 | I37: =IFERROR(I36/I16,0) -> 0.090801874 | J37: =IFERROR(J36/J16,0) -> 0.074880745 | ... O37: =IFERROR(O36/O16,0) -> 0.10513089
B39: Fixed OH absorbed at standard rate (Standard labour hours*Standard fixed OH absorption rate) | C39: =C18*Assumptions!$C$31 -> 5850000 | D39: =D18*Assumptions!$C$31 -> 6175000 | E39: =E18*Assumptions!$C$31 -> 6500000 | F39: =F18*Assumptions!$C$31 -> 6825000 | G39: =G18*Assumptions!$C$31 -> 7150000 | H39: =H18*Assumptions!$C$31 -> 6825000 | I39: =I18*Assumptions!$C$31 -> 6175000 | J39: =J18*Assumptions!$C$31 -> 5850000 | ... N39: =N18*Assumptions!$C$31 -> 6500000 | O39: =SUM(C39:N39) -> 78000000
B40: Over / (under) absorption | C40: =C39-C34 -> -650000 | D40: =D39-D34 -> -325000 | E40: =E39-E34 -> 0 | F40: =F39-F34 -> 325000 | G40: =G39-G34 -> 650000 | H40: =H39-H34 -> 325000 | I40: =I39-I34 -> -325000 | J40: =J39-J34 -> -650000 | ... N40: =N39-N34 -> 0 | O40: =SUM(C40:N40) -> 9.3132257e-09

Sheet Actuals & Forecast
B1: Actuals (Apr-Sep 2026) & Rolling Forecast (Oct 2026-Mar 2027)
B3: Month | C3: =DATE(2026,4,1) -> 46113 | D3: =EDATE(C3,1) -> 46143 | E3: =EDATE(D3,1) -> 46174 | F3: =EDATE(E3,1) -> 46204 | G3: =EDATE(F3,1) -> 46235 | H3: =EDATE(G3,1) -> 46266 | I3: =EDATE(H3,1) -> 46296 | J3: =EDATE(I3,1) -> 46327 | K3: =EDATE(J3,1) -> 46357 | ... N3: =EDATE(M3,1) -> 46447 | O3: FY Total
B4: Actual / Forecast | C4: Actual | D4: Actual | E4: Actual | F4: Actual | G4: Actual | H4: Actual | I4: Forecast | J4: Forecast | K4: Forecast | L4: Forecast | M4: Forecast | N4: Forecast
B6: Volume (units)
B7: Alpha | C7: 9360 | D7: 9310 | E7: 10600 | F7: 10605 | G7: 10450 | H7: 10815 | I7: =(Assumptions!$C$5/12*Assumptions!I$19*(1+Assumptions!$C$35)) -> 9785 | J7: =(Assumptions!$C$5/12*Assumptions!J$19*(1+Assumptions!$C$35)) -> 9270 | K7: =(Assumptions!$C$5/12*Assumptions!K$19*(1+Assumptions!$C$35)) -> 9785 | L7: =(Assumptions!$C$5/12*Assumptions!L$19*(1+Assumptions!$C$35)) -> 10815 | M7: =(Assumptions!$C$5/12*Assumptions!M$19*(1+Assumptions!$C$35)) -> 11330 | N7: =(Assumptions!$C$5/12*Assumptions!N$19*(1+Assumptions!$C$35)) -> 10300 | O7: =SUM(C7:N7) -> 122425
B8: Beta | C8: 5184 | D8: 5814 | E8: 5940 | F8: 6615 | G8: 7128 | H8: 6363 | I8: =(Assumptions!$D$5/12*Assumptions!I$19*(1+Assumptions!$C$35)) -> 5871 | J8: =(Assumptions!$D$5/12*Assumptions!J$19*(1+Assumptions!$C$35)) -> 5562 | K8: =(Assumptions!$D$5/12*Assumptions!K$19*(1+Assumptions!$C$35)) -> 5871 | L8: =(Assumptions!$D$5/12*Assumptions!L$19*(1+Assumptions!$C$35)) -> 6489 | M8: =(Assumptions!$D$5/12*Assumptions!M$19*(1+Assumptions!$C$35)) -> 6798 | N8: =(Assumptions!$D$5/12*Assumptions!N$19*(1+Assumptions!$C$35)) -> 6180 | O8: =SUM(C8:N8) -> 73815
B9: Gamma | C9: 3713 | D9: 3741 | E9: 3638 | F9: 3662 | G9: 4208 | H9: 4174 | I9: =(Assumptions!$E$5/12*Assumptions!I$19*(1+Assumptions!$C$35)) -> 3669.375 | J9: =(Assumptions!$E$5/12*Assumptions!J$19*(1+Assumptions!$C$35)) -> 3476.25 | K9: =(Assumptions!$E$5/12*Assumptions!K$19*(1+Assumptions!$C$35)) -> 3669.375 | L9: =(Assumptions!$E$5/12*Assumptions!L$19*(1+Assumptions!$C$35)) -> 4055.625 | M9: =(Assumptions!$E$5/12*Assumptions!M$19*(1+Assumptions!$C$35)) -> 4248.75 | N9: =(Assumptions!$E$5/12*Assumptions!N$19*(1+Assumptions!$C$35)) -> 3862.5 | O9: =SUM(C9:N9) -> 46117.875
B10: Total units | C10: =SUM(C7:C9) -> 18257 | D10: =SUM(D7:D9) -> 18865 | E10: =SUM(E7:E9) -> 20178 | F10: =SUM(F7:F9) -> 20882 | G10: =SUM(G7:G9) -> 21786 | H10: =SUM(H7:H9) -> 21352 | I10: =SUM(I7:I9) -> 19325.375 | J10: =SUM(J7:J9) -> 18308.25 | ... N10: =SUM(N7:N9) -> 20342.5 | O10: =SUM(C10:N10) -> 242357.88
B12: Achieved Selling Price (₹ / unit)
B13: Alpha | C13: 862 | D13: 855 | E13: 845 | F13: 870 | G13: 858 | H13: 866 | I13: =Assumptions!$C$6*(1+Assumptions!$C$36) -> 862.75 | J13: =Assumptions!$C$6*(1+Assumptions!$C$36) -> 862.75 | K13: =Assumptions!$C$6*(1+Assumptions!$C$36) -> 862.75 | L13: =Assumptions!$C$6*(1+Assumptions!$C$36) -> 862.75 | M13: =Assumptions!$C$6*(1+Assumptions!$C$36) -> 862.75 | N13: =Assumptions!$C$6*(1+Assumptions!$C$36) -> 862.75 | O13: =IFERROR(O18/O7,0) -> 861.07612
B14: Beta | C14: 1235 | D14: 1262 | E14: 1270 | F14: 1248 | G14: 1255 | H14: 1240 | I14: =Assumptions!$D$6*(1+Assumptions!$C$36) -> 1268.75 | J14: =Assumptions!$D$6*(1+Assumptions!$C$36) -> 1268.75 | K14: =Assumptions!$D$6*(1+Assumptions!$C$36) -> 1268.75 | L14: =Assumptions!$D$6*(1+Assumptions!$C$36) -> 1268.75 | M14: =Assumptions!$D$6*(1+Assumptions!$C$36) -> 1268.75 | N14: =Assumptions!$D$6*(1+Assumptions!$C$36) -> 1268.75 | O14: =IFERROR(O19/O8,0) -> 1260.2831
B15: Gamma | C15: 2150 | D15: 2120 | E15: 2085 | F15: 2110 | G15: 2160 | H15: 2135 | I15: =Assumptions!$E$6*(1+Assumptions!$C$36) -> 2131.5 | J15: =Assumptions!$E$6*(1+Assumptions!$C$36) -> 2131.5 | K15: =Assumptions!$E$6*(1+Assumptions!$C$36) -> 2131.5 | L15: =Assumptions!$E$6*(1+Assumptions!$C$36) -> 2131.5 | M15: =Assumptions!$E$6*(1+Assumptions!$C$36) -> 2131.5 | N15: =Assumptions!$E$6*(1+Assumptions!$C$36) -> 2131.5 | O15: =IFERROR(O20/O9,0) -> 2129.5985
B17: Revenue (₹)
B18: Alpha | C18: =C7*C13 -> 8068320 | D18: =D7*D13 -> 7960050 | E18: =E7*E13 -> 8957000 | F18: =F7*F13 -> 9226350 | G18: =G7*G13 -> 8966100 | H18: =H7*H13 -> 9365790 | I18: =I7*I13 -> 8442008.7 | J18: =J7*J13 -> 7997692.5 | ... N18: =N7*N13 -> 8886325 | O18: =SUM(C18:N18) -> 1.0541724e+08
B19: Beta | C19: =C8*C14 -> 6402240 | D19: =D8*D14 -> 7337268 | E19: =E8*E14 -> 7543800 | F19: =F8*F14 -> 8255520 | G19: =G8*G14 -> 8945640 | H19: =H8*H14 -> 7890120 | I19: =I8*I14 -> 7448831.2 | J19: =J8*J14 -> 7056787.5 | ... N19: =N8*N14 -> 7840875 | O19: =SUM(C19:N19) -> 93027794
B20: Gamma | C20: =C9*C15 -> 7982950 | D20: =D9*D15 -> 7930920 | E20: =E9*E15 -> 7585230 | F20: =F9*F15 -> 7726820 | G20: =G9*G15 -> 9089280 | H20: =H9*H15 -> 8911490 | I20: =I9*I15 -> 7821272.8 | J20: =J9*J15 -> 7409626.9 | ... N20: =N9*N15 -> 8232918.8 | O20: =SUM(C20:N20) -> 98212557
B21: Total revenue | C21: =SUM(C18:C20) -> 22453510 | D21: =SUM(D18:D20) -> 23228238 | E21: =SUM(E18:E20) -> 24086030 | F21: =SUM(F18:F20) -> 25208690 | G21: =SUM(G18:G20) -> 27001020 | H21: =SUM(H18:H20) -> 26167400 | I21: =SUM(I18:I20) -> 23712113 | J21: =SUM(J18:J20) -> 22464107 | ... N21: =SUM(N18:N20) -> 24960119 | O21: =SUM(C21:N21) -> 2.9665759e+08
B23: Labour
B24: Actual labour hours | C24: 13681 | D24: 13933 | E24: 15138 | F24: 14839 | G24: 16297 | H24: 16127 | I24: =I26*Assumptions!$C$41 -> 14272.401 | J24: =J26*Assumptions!$C$41 -> 13521.222 | K24: =K26*Assumptions!$C$41 -> 14272.401 | L24: =L26*Assumptions!$C$41 -> 15774.759 | M24: =M26*Assumptions!$C$41 -> 16525.938 | N24: =N26*Assumptions!$C$41 -> 15023.58 | O24: =SUM(C24:N24) -> 179405.3
B25: Actual labour rate (₹ / hour) | C25: 268 | D25: 274 | E25: 271 | F25: 279 | G25: 276 | H25: 273 | I25: =IFERROR((I7*Assumptions!$C$8*Assumptions!$C$9+I8*Assumptions!$D$8*Assumptions!$D$9+I9*Assumptions!$E$8*Assumptions!$E$9)/I26,0)*(1+Assumptions!$C$38) -> 293.26573 | J25: =IFERROR((J7*Assumptions!$C$8*Assumptions!$C$9+J8*Assumptions!$D$8*Assumptions!$D$9+J9*Assumptions!$E$8*Assumptions!$E$9)/J26,0)*(1+Assumptions!$C$38) -> 293.26573 | K25: =IFERROR((K7*Assumptions!$C$8*Assumptions!$C$9+K8*Assumptions!$D$8*Assumptions!$D$9+K9*Assumptions!$E$8*Assumptions!$E$9)/K26,0)*(1+Assumptions!$C$38) -> 293.26573 | L25: =IFERROR((L7*Assumptions!$C$8*Assumptions!$C$9+L8*Assumptions!$D$8*Assumptions!$D$9+L9*Assumptions!$E$8*Assumptions!$E$9)/L26,0)*(1+Assumptions!$C$38) -> 293.26573 | M25: =IFERROR((M7*Assumptions!$C$8*Assumptions!$C$9+M8*Assumptions!$D$8*Assumptions!$D$9+M9*Assumptions!$E$8*Assumptions!$E$9)/M26,0)*(1+Assumptions!$C$38) -> 293.26573 | N25: =IFERROR((N7*Assumptions!$C$8*Assumptions!$C$9+N8*Assumptions!$D$8*Assumptions!$D$9+N9*Assumptions!$E$8*Assumptions!$E$9)/N26,0)*(1+Assumptions!$C$38) -> 293.26573 | O25: =IFERROR(O44/O24,0) -> 283.39399
B26: Standard hours for actual output | C26: =C7*Assumptions!$C$8+C8*Assumptions!$D$8+C9*Assumptions!$E$8 -> 13282.8 | D26: =D7*Assumptions!$C$8+D8*Assumptions!$D$8+D9*Assumptions!$E$8 -> 13795.4 | E26: =E7*Assumptions!$C$8+E8*Assumptions!$D$8+E9*Assumptions!$E$8 -> 14417.6 | F26: =F7*Assumptions!$C$8+F8*Assumptions!$D$8+F9*Assumptions!$E$8 -> 14988.9 | G26: =G7*Assumptions!$C$8+G8*Assumptions!$D$8+G9*Assumptions!$E$8 -> 15977 | H26: =H7*Assumptions!$C$8+H8*Assumptions!$D$8+H9*Assumptions!$E$8 -> 15506.7 | I26: =I7*Assumptions!$C$8+I8*Assumptions!$D$8+I9*Assumptions!$E$8 -> 13992.55 | J26: =J7*Assumptions!$C$8+J8*Assumptions!$D$8+J9*Assumptions!$E$8 -> 13256.1 | ... N26: =N7*Assumptions!$C$8+N8*Assumptions!$D$8+N9*Assumptions!$E$8 -> 14729 | O26: =SUM(C26:N26) -> 175605.95
B28: Actual Variable Overhead By Department
B29: Machining | C29: 845000 | D29: 844000 | E29: 945000 | F29: 881000 | G29: 997000 | H29: 1016000 | I29: =I$24*Assumptions!$D$24*(1+Assumptions!$C$39) -> 882034.38 | J29: =J$24*Assumptions!$D$24*(1+Assumptions!$C$39) -> 835611.52 | K29: =K$24*Assumptions!$D$24*(1+Assumptions!$C$39) -> 882034.38 | L29: =L$24*Assumptions!$D$24*(1+Assumptions!$C$39) -> 974880.11 | M29: =M$24*Assumptions!$D$24*(1+Assumptions!$C$39) -> 1021303 | N29: =N$24*Assumptions!$D$24*(1+Assumptions!$C$39) -> 928457.24 | O29: =SUM(C29:N29) -> 11052321
B30: Assembly | C30: 469000 | D30: 497000 | E30: 535000 | F30: 535000 | G30: 565000 | H30: 576000 | I30: =I$24*Assumptions!$D$25*(1+Assumptions!$C$39) -> 514520.06 | J30: =J$24*Assumptions!$D$25*(1+Assumptions!$C$39) -> 487440.05 | K30: =K$24*Assumptions!$D$25*(1+Assumptions!$C$39) -> 514520.06 | L30: =L$24*Assumptions!$D$25*(1+Assumptions!$C$39) -> 568680.06 | M30: =M$24*Assumptions!$D$25*(1+Assumptions!$C$39) -> 595760.06 | N30: =N$24*Assumptions!$D$25*(1+Assumptions!$C$39) -> 541600.06 | O30: =SUM(C30:N30) -> 6399520.4
B31: Packing | C31: 215000 | D31: 215000 | E31: 225000 | F31: 227000 | G31: 254000 | H31: 244000 | I31: =I$24*Assumptions!$D$26*(1+Assumptions!$C$39) -> 220508.6 | J31: =J$24*Assumptions!$D$26*(1+Assumptions!$C$39) -> 208902.88 | K31: =K$24*Assumptions!$D$26*(1+Assumptions!$C$39) -> 220508.6 | L31: =L$24*Assumptions!$D$26*(1+Assumptions!$C$39) -> 243720.03 | M31: =M$24*Assumptions!$D$26*(1+Assumptions!$C$39) -> 255325.74 | N31: =N$24*Assumptions!$D$26*(1+Assumptions!$C$39) -> 232114.31 | O31: =SUM(C31:N31) -> 2761080.2
B32: Admin & Support | C32: 138000 | D32: 137000 | E32: 154000 | F32: 148000 | G32: 168000 | H32: 160000 | I32: =I$24*Assumptions!$D$27*(1+Assumptions!$C$39) -> 147005.73 | J32: =J$24*Assumptions!$D$27*(1+Assumptions!$C$39) -> 139268.59 | K32: =K$24*Assumptions!$D$27*(1+Assumptions!$C$39) -> 147005.73 | L32: =L$24*Assumptions!$D$27*(1+Assumptions!$C$39) -> 162480.02 | M32: =M$24*Assumptions!$D$27*(1+Assumptions!$C$39) -> 170217.16 | N32: =N$24*Assumptions!$D$27*(1+Assumptions!$C$39) -> 154742.87 | O32: =SUM(C32:N32) -> 1825720.1
B33: Total variable overhead | C33: =SUM(C29:C32) -> 1667000 | D33: =SUM(D29:D32) -> 1693000 | E33: =SUM(E29:E32) -> 1859000 | F33: =SUM(F29:F32) -> 1791000 | G33: =SUM(G29:G32) -> 1984000 | H33: =SUM(H29:H32) -> 1996000 | I33: =SUM(I29:I32) -> 1764068.8 | J33: =SUM(J29:J32) -> 1671223 | ... N33: =SUM(N29:N32) -> 1856914.5 | O33: =SUM(C33:N33) -> 22038641
B35: Actual Fixed Overhead By Department
B36: Machining | C36: 2720000 | D36: 2640000 | E36: 2747000 | F36: 2693000 | G36: 2773000 | H36: 2667000 | I36: =Assumptions!$C$24/12*(1+Assumptions!$C$40) -> 2733333.3 | J36: =Assumptions!$C$24/12*(1+Assumptions!$C$40) -> 2733333.3 | K36: =Assumptions!$C$24/12*(1+Assumptions!$C$40) -> 2733333.3 | L36: =Assumptions!$C$24/12*(1+Assumptions!$C$40) -> 2733333.3 | M36: =Assumptions!$C$24/12*(1+Assumptions!$C$40) -> 2733333.3 | N36: =Assumptions!$C$24/12*(1+Assumptions!$C$40) -> 2733333.3 | O36: =SUM(C36:N36) -> 32640000
B37: Assembly | C37: 1733000 | D37: 1768000 | E37: 1750000 | F37: 1785000 | G37: 1715000 | H37: 1803000 | I37: =Assumptions!$C$25/12*(1+Assumptions!$C$40) -> 1793750 | J37: =Assumptions!$C$25/12*(1+Assumptions!$C$40) -> 1793750 | K37: =Assumptions!$C$25/12*(1+Assumptions!$C$40) -> 1793750 | L37: =Assumptions!$C$25/12*(1+Assumptions!$C$40) -> 1793750 | M37: =Assumptions!$C$25/12*(1+Assumptions!$C$40) -> 1793750 | N37: =Assumptions!$C$25/12*(1+Assumptions!$C$40) -> 1793750 | O37: =SUM(C37:N37) -> 21316500
B38: Packing | C38: 773000 | D38: 765000 | E38: 743000 | F38: 758000 | G38: 750000 | H38: 765000 | I38: =Assumptions!$C$26/12*(1+Assumptions!$C$40) -> 768750 | J38: =Assumptions!$C$26/12*(1+Assumptions!$C$40) -> 768750 | K38: =Assumptions!$C$26/12*(1+Assumptions!$C$40) -> 768750 | L38: =Assumptions!$C$26/12*(1+Assumptions!$C$40) -> 768750 | M38: =Assumptions!$C$26/12*(1+Assumptions!$C$40) -> 768750 | N38: =Assumptions!$C$26/12*(1+Assumptions!$C$40) -> 768750 | O38: =SUM(C38:N38) -> 9166500
B39: Admin & Support | C39: 1347000 | D39: 1333000 | E39: 1360000 | F39: 1320000 | G39: 1373000 | H39: 1347000 | I39: =Assumptions!$C$27/12*(1+Assumptions!$C$40) -> 1366666.7 | J39: =Assumptions!$C$27/12*(1+Assumptions!$C$40) -> 1366666.7 | K39: =Assumptions!$C$27/12*(1+Assumptions!$C$40) -> 1366666.7 | L39: =Assumptions!$C$27/12*(1+Assumptions!$C$40) -> 1366666.7 | M39: =Assumptions!$C$27/12*(1+Assumptions!$C$40) -> 1366666.7 | N39: =Assumptions!$C$27/12*(1+Assumptions!$C$40) -> 1366666.7 | O39: =SUM(C39:N39) -> 16280000
B40: Total fixed overhead | C40: =SUM(C36:C39) -> 6573000 | D40: =SUM(D36:D39) -> 6506000 | E40: =SUM(E36:E39) -> 6600000 | F40: =SUM(F36:F39) -> 6556000 | G40: =SUM(G36:G39) -> 6611000 | H40: =SUM(H36:H39) -> 6582000 | I40: =SUM(I36:I39) -> 6662500 | J40: =SUM(J36:J39) -> 6662500 | ... N40: =SUM(N36:N39) -> 6662500 | O40: =SUM(C40:N40) -> 79403000
B42: Cost Summary
B43: Direct material | C43: 8699000 | D43: 8838000 | E43: 9595000 | F43: 9667000 | G43: 10114000 | H43: 10236000 | I43: =(I7*Assumptions!$C$7+I8*Assumptions!$D$7+I9*Assumptions!$E$7)*(1+Assumptions!$C$37)*Assumptions!$C$42 -> 9456241.6 | J43: =(J7*Assumptions!$C$7+J8*Assumptions!$D$7+J9*Assumptions!$E$7)*(1+Assumptions!$C$37)*Assumptions!$C$42 -> 8958544.7 | K43: =(K7*Assumptions!$C$7+K8*Assumptions!$D$7+K9*Assumptions!$E$7)*(1+Assumptions!$C$37)*Assumptions!$C$42 -> 9456241.6 | L43: =(L7*Assumptions!$C$7+L8*Assumptions!$D$7+L9*Assumptions!$E$7)*(1+Assumptions!$C$37)*Assumptions!$C$42 -> 10451635 | M43: =(M7*Assumptions!$C$7+M8*Assumptions!$D$7+M9*Assumptions!$E$7)*(1+Assumptions!$C$37)*Assumptions!$C$42 -> 10949332 | N43: =(N7*Assumptions!$C$7+N8*Assumptions!$D$7+N9*Assumptions!$E$7)*(1+Assumptions!$C$37)*Assumptions!$C$42 -> 9953938.5 | O43: =SUM(C43:N43) -> 1.1637493e+08
B44: Direct labour | C44: =C24*C25 -> 3666508 | D44: =D24*D25 -> 3817642 | E44: =E24*E25 -> 4102398 | F44: =F24*F25 -> 4140081 | G44: =G24*G25 -> 4497972 | H44: =H24*H25 -> 4402671 | I44: =I24*I25 -> 4185606.2 | J44: =J24*J25 -> 3965311.1 | ... N44: =N24*N25 -> 4405901.2 | O44: =SUM(C44:N44) -> 50842384
B45: Variable overhead | C45: =C33 -> 1667000 | D45: =D33 -> 1693000 | E45: =E33 -> 1859000 | F45: =F33 -> 1791000 | G45: =G33 -> 1984000 | H45: =H33 -> 1996000 | I45: =I33 -> 1764068.8 | J45: =J33 -> 1671223 | ... N45: =N33 -> 1856914.5 | O45: =SUM(C45:N45) -> 22038641
B46: Total variable cost | C46: =SUM(C43:C45) -> 14032508 | D46: =SUM(D43:D45) -> 14348642 | E46: =SUM(E43:E45) -> 15556398 | F46: =SUM(F43:F45) -> 15598081 | G46: =SUM(G43:G45) -> 16595972 | H46: =SUM(H43:H45) -> 16634671 | I46: =SUM(I43:I45) -> 15405917 | J46: =SUM(J43:J45) -> 14595079 | ... N46: =SUM(N43:N45) -> 16216754 | O46: =SUM(C46:N46) -> 1.8925596e+08
B48: Contribution | C48: =C21-C46 -> 8421002 | D48: =D21-D46 -> 8879596 | E48: =E21-E46 -> 8529632 | F48: =F21-F46 -> 9610609 | G48: =G21-G46 -> 10405048 | H48: =H21-H46 -> 9532729 | I48: =I21-I46 -> 8306196.3 | J48: =J21-J46 -> 7869028.1 | ... N48: =N21-N46 -> 8743364.5 | O48: =SUM(C48:N48) -> 1.0740163e+08
B49: Contribution margin % | C49: =IFERROR(C48/C21,0) -> 0.37504167 | D49: =IFERROR(D48/D21,0) -> 0.38227592 | E49: =IFERROR(E48/E21,0) -> 0.35413192 | F49: =IFERROR(F48/F21,0) -> 0.38124191 | G49: =IFERROR(G48/G21,0) -> 0.38535759 | H49: =IFERROR(H48/H21,0) -> 0.36429791 | I49: =IFERROR(I48/I21,0) -> 0.35029339 | J49: =IFERROR(J48/J21,0) -> 0.35029339 | ... O49: =IFERROR(O48/O21,0) -> 0.36203905
B51: Operating Profit | C51: =C48-C40 -> 1848002 | D51: =D48-D40 -> 2373596 | E51: =E48-E40 -> 1929632 | F51: =F48-F40 -> 3054609 | G51: =G48-G40 -> 3794048 | H51: =H48-H40 -> 2950729 | I51: =I48-I40 -> 1643696.3 | J51: =J48-J40 -> 1206528.1 | ... N51: =N48-N40 -> 2080864.5 | O51: =SUM(C51:N51) -> 27998635
B52: Operating margin % | C52: =IFERROR(C51/C21,0) -> 0.08230348 | D52: =IFERROR(D51/D21,0) -> 0.1021858 | E52: =IFERROR(E51/E21,0) -> 0.080114157 | F52: =IFERROR(F51/F21,0) -> 0.12117286 | G52: =IFERROR(G51/G21,0) -> 0.14051499 | H52: =IFERROR(H51/H21,0) -> 0.11276355 | I52: =IFERROR(I51/I21,0) -> 0.069318845 | J52: =IFERROR(J51/J21,0) -> 0.053709148 | ... O52: =IFERROR(O51/O21,0) -> 0.094380307
B54: Fixed OH absorbed at standard rate | C54: =C26*Assumptions!$C$31 -> 6037636.4 | D54: =D26*Assumptions!$C$31 -> 6270636.4 | E54: =E26*Assumptions!$C$31 -> 6553454.5 | F54: =F26*Assumptions!$C$31 -> 6813136.4 | G54: =G26*Assumptions!$C$31 -> 7262272.7 | H54: =H26*Assumptions!$C$31 -> 7048500 | I54: =I26*Assumptions!$C$31 -> 6360250 | J54: =J26*Assumptions!$C$31 -> 6025500 | ... N54: =N26*Assumptions!$C$31 -> 6695000 | O54: =SUM(C54:N54) -> 79820886
B55: Over / (under) absorption | C55: =C54-C40 -> -535363.64 | D55: =D54-D40 -> -235363.64 | E55: =E54-E40 -> -46545.455 | F55: =F54-F40 -> 257136.36 | G55: =G54-G40 -> 651272.73 | H55: =H54-H40 -> 466500 | I55: =I54-I40 -> -302250 | J55: =J54-J40 -> -637000 | ... N55: =N54-N40 -> 32500 | O55: =SUM(C55:N55) -> 417886.36

Sheet Sales Variances
B1: Sales Variance Analysis - Price, Volume, Mix & Quantity
B3: Month | C3: =DATE(2026,4,1) -> 46113 | D3: =EDATE(C3,1) -> 46143 | E3: =EDATE(D3,1) -> 46174 | F3: =EDATE(E3,1) -> 46204 | G3: =EDATE(F3,1) -> 46235 | H3: =EDATE(G3,1) -> 46266 | I3: =EDATE(H3,1) -> 46296 | J3: =EDATE(I3,1) -> 46327 | K3: =EDATE(J3,1) -> 46357 | ... N3: =EDATE(M3,1) -> 46447 | O3: FY Total
B4: Actual / Forecast | C4: Actual | D4: Actual | E4: Actual | F4: Actual | G4: Actual | H4: Actual | I4: Forecast | J4: Forecast | K4: Forecast | L4: Forecast | M4: Forecast | N4: Forecast
B6: Alpha
B7: Actual volume (units) | C7: ='Actuals & Forecast'!C7 -> 9360 | D7: ='Actuals & Forecast'!D7 -> 9310 | E7: ='Actuals & Forecast'!E7 -> 10600 | F7: ='Actuals & Forecast'!F7 -> 10605 | G7: ='Actuals & Forecast'!G7 -> 10450 | H7: ='Actuals & Forecast'!H7 -> 10815 | I7: ='Actuals & Forecast'!I7 -> 9785 | J7: ='Actuals & Forecast'!J7 -> 9270 | ... N7: ='Actuals & Forecast'!N7 -> 10300 | O7: =SUM(C7:N7) -> 122425
B8: Budget volume (units) | C8: ='Rolling Budget'!C7 -> 9000 | D8: ='Rolling Budget'!D7 -> 9500 | E8: ='Rolling Budget'!E7 -> 10000 | F8: ='Rolling Budget'!F7 -> 10500 | G8: ='Rolling Budget'!G7 -> 11000 | H8: ='Rolling Budget'!H7 -> 10500 | I8: ='Rolling Budget'!I7 -> 9500 | J8: ='Rolling Budget'!J7 -> 9000 | ... N8: ='Rolling Budget'!N7 -> 10000 | O8: =SUM(C8:N8) -> 120000
B9: Volume difference (units) | C9: =C7-C8 -> 360 | D9: =D7-D8 -> -190 | E9: =E7-E8 -> 600 | F9: =F7-F8 -> 105 | G9: =G7-G8 -> -550 | H9: =H7-H8 -> 315 | I9: =I7-I8 -> 285 | J9: =J7-J8 -> 270 | ... N9: =N7-N8 -> 300 | O9: =SUM(C9:N9) -> 2425
B10: Achieved price (₹ / unit) | C10: ='Actuals & Forecast'!C13 -> 862 | D10: ='Actuals & Forecast'!D13 -> 855 | E10: ='Actuals & Forecast'!E13 -> 845 | F10: ='Actuals & Forecast'!F13 -> 870 | G10: ='Actuals & Forecast'!G13 -> 858 | H10: ='Actuals & Forecast'!H13 -> 866 | I10: ='Actuals & Forecast'!I13 -> 862.75 | J10: ='Actuals & Forecast'!J13 -> 862.75 | ... N10: ='Actuals & Forecast'!N13 -> 862.75 | O10: =IFERROR(O13/O7+O11,0) -> 861.07612
B11: Budget price (₹ / unit) | C11: =Assumptions!$C$6 -> 850 | D11: =Assumptions!$C$6 -> 850 | E11: =Assumptions!$C$6 -> 850 | F11: =Assumptions!$C$6 -> 850 | G11: =Assumptions!$C$6 -> 850 | H11: =Assumptions!$C$6 -> 850 | I11: =Assumptions!$C$6 -> 850 | J11: =Assumptions!$C$6 -> 850 | ... O11: =Assumptions!$C$6 -> 850
B12: Standard contribution (₹ / unit) | C12: =Assumptions!$C$13 -> 340 | D12: =Assumptions!$C$13 -> 340 | E12: =Assumptions!$C$13 -> 340 | F12: =Assumptions!$C$13 -> 340 | G12: =Assumptions!$C$13 -> 340 | H12: =Assumptions!$C$13 -> 340 | I12: =Assumptions!$C$13 -> 340 | J12: =Assumptions!$C$13 -> 340 | ... O12: =Assumptions!$C$13 -> 340
B13: Sales price variance (₹) = (Actual price − Budget price) × Actual qty | C13: =(C10-C11)*C7 -> 112320 | D13: =(D10-D11)*D7 -> 46550 | E13: =(E10-E11)*E7 -> -53000 | F13: =(F10-F11)*F7 -> 212100 | G13: =(G10-G11)*G7 -> 83600 | H13: =(H10-H11)*H7 -> 173040 | I13: =(I10-I11)*I7 -> 124758.75 | J13: =(J10-J11)*J7 -> 118192.5 | ... N13: =(N10-N11)*N7 -> 131325 | O13: =SUM(C13:N13) -> 1355993.7
B14: Sales volume contribution variance (₹) = (Actual qty − Budget qty) × Std contribution | C14: =(C7-C8)*C12 -> 122400 | D14: =(D7-D8)*D12 -> -64600 | E14: =(E7-E8)*E12 -> 204000 | F14: =(F7-F8)*F12 -> 35700 | G14: =(G7-G8)*G12 -> -187000 | H14: =(H7-H8)*H12 -> 107100 | I14: =(I7-I8)*I12 -> 96900 | J14: =(J7-J8)*J12 -> 91800 | ... N14: =(N7-N8)*N12 -> 102000 | O14: =SUM(C14:N14) -> 824500
B15: Sales mix variance = (Actual qty − Total actual qty × Budget mix %) × Std contribution | C15: =(C7-'Actuals & Forecast'!C$10*Assumptions!$C$15)*C12 -> 39422.785 | D15: =(D7-'Actuals & Forecast'!D$10*Assumptions!$C$15)*D12 -> -82245.57 | E15: =(E7-'Actuals & Forecast'!E$10*Assumptions!$C$15)*E12 -> 130318.99 | F15: =(F7-'Actuals & Forecast'!F$10*Assumptions!$C$15)*F12 -> 10824.051 | G15: =(G7-'Actuals & Forecast'!G$10*Assumptions!$C$15)*G12 -> -197501.27 | H15: =(H7-'Actuals & Forecast'!H$10*Assumptions!$C$15)*H12 -> 1312.6582 | I15: =(I7-'Actuals & Forecast'!I$10*Assumptions!$C$15)*I12 -> 0 | J15: =(J7-'Actuals & Forecast'!J$10*Assumptions!$C$15)*J12 -> 0 | ... N15: =(N7-'Actuals & Forecast'!N$10*Assumptions!$C$15)*N12 -> 0 | O15: =SUM(C15:N15) -> -97868.354
B16: Sales quantity variance = (Total actual qty × Budget mix % − Budget qty) × Std contribution | C16: =('Actuals & Forecast'!C$10*Assumptions!$C$15-C8)*C12 -> 82977.215 | D16: =('Actuals & Forecast'!D$10*Assumptions!$C$15-D8)*D12 -> 17645.57 | E16: =('Actuals & Forecast'!E$10*Assumptions!$C$15-E8)*E12 -> 73681.013 | F16: =('Actuals & Forecast'!F$10*Assumptions!$C$15-F8)*F12 -> 24875.949 | G16: =('Actuals & Forecast'!G$10*Assumptions!$C$15-G8)*G12 -> 10501.266 | H16: =('Actuals & Forecast'!H$10*Assumptions!$C$15-H8)*H12 -> 105787.34 | I16: =('Actuals & Forecast'!I$10*Assumptions!$C$15-I8)*I12 -> 96900 | J16: =('Actuals & Forecast'!J$10*Assumptions!$C$15-J8)*J12 -> 91800 | ... N16: =('Actuals & Forecast'!N$10*Assumptions!$C$15-N8)*N12 -> 102000 | O16: =SUM(C16:N16) -> 922368.35
B17: Total sales variance (₹) = Price variance + Volume variance | C17: =C13+C14 -> 234720 | D17: =D13+D14 -> -18050 | E17: =E13+E14 -> 151000 | F17: =F13+F14 -> 247800 | G17: =G13+G14 -> -103400 | H17: =H13+H14 -> 280140 | I17: =I13+I14 -> 221658.75 | J17: =J13+J14 -> 209992.5 | ... N17: =N13+N14 -> 233325 | O17: =SUM(C17:N17) -> 2180493.7
B19: Beta
B20: Actual volume (units) | C20: ='Actuals & Forecast'!C8 -> 5184 | D20: ='Actuals & Forecast'!D8 -> 5814 | E20: ='Actuals & Forecast'!E8 -> 5940 | F20: ='Actuals & Forecast'!F8 -> 6615 | G20: ='Actuals & Forecast'!G8 -> 7128 | H20: ='Actuals & Forecast'!H8 -> 6363 | I20: ='Actuals & Forecast'!I8 -> 5871 | J20: ='Actuals & Forecast'!J8 -> 5562 | ... N20: ='Actuals & Forecast'!N8 -> 6180 | O20: =SUM(C20:N20) -> 73815
B21: Budget volume (units) | C21: ='Rolling Budget'!C8 -> 5400 | D21: ='Rolling Budget'!D8 -> 5700 | E21: ='Rolling Budget'!E8 -> 6000 | F21: ='Rolling Budget'!F8 -> 6300 | G21: ='Rolling Budget'!G8 -> 6600 | H21: ='Rolling Budget'!H8 -> 6300 | I21: ='Rolling Budget'!I8 -> 5700 | J21: ='Rolling Budget'!J8 -> 5400 | ... N21: ='Rolling Budget'!N8 -> 6000 | O21: =SUM(C21:N21) -> 72000
B22: Volume difference (units) | C22: =C20-C21 -> -216 | D22: =D20-D21 -> 114 | E22: =E20-E21 -> -60 | F22: =F20-F21 -> 315 | G22: =G20-G21 -> 528 | H22: =H20-H21 -> 63 | I22: =I20-I21 -> 171 | J22: =J20-J21 -> 162 | ... N22: =N20-N21 -> 180 | O22: =SUM(C22:N22) -> 1815
B23: Achieved price (₹ / unit) | C23: ='Actuals & Forecast'!C14 -> 1235 | D23: ='Actuals & Forecast'!D14 -> 1262 | E23: ='Actuals & Forecast'!E14 -> 1270 | F23: ='Actuals & Forecast'!F14 -> 1248 | G23: ='Actuals & Forecast'!G14 -> 1255 | H23: ='Actuals & Forecast'!H14 -> 1240 | I23: ='Actuals & Forecast'!I14 -> 1268.75 | J23: ='Actuals & Forecast'!J14 -> 1268.75 | ... N23: ='Actuals & Forecast'!N14 -> 1268.75 | O23: =IFERROR(O26/O20+O24,0) -> 1260.2831
B24: Budget price (₹ / unit) | C24: =Assumptions!$D$6 -> 1250 | D24: =Assumptions!$D$6 -> 1250 | E24: =Assumptions!$D$6 -> 1250 | F24: =Assumptions!$D$6 -> 1250 | G24: =Assumptions!$D$6 -> 1250 | H24: =Assumptions!$D$6 -> 1250 | I24: =Assumptions!$D$6 -> 1250 | J24: =Assumptions!$D$6 -> 1250 | ... O24: =Assumptions!$D$6 -> 1250
B25: Standard contribution (₹ / unit) | C25: =Assumptions!$D$13 -> 450 | D25: =Assumptions!$D$13 -> 450 | E25: =Assumptions!$D$13 -> 450 | F25: =Assumptions!$D$13 -> 450 | G25: =Assumptions!$D$13 -> 450 | H25: =Assumptions!$D$13 -> 450 | I25: =Assumptions!$D$13 -> 450 | J25: =Assumptions!$D$13 -> 450 | ... O25: =Assumptions!$D$13 -> 450
B26: Sales price variance (₹) = (Actual price − Budget price) × Actual qty | C26: =(C23-C24)*C20 -> -77760 | D26: =(D23-D24)*D20 -> 69768 | E26: =(E23-E24)*E20 -> 118800 | F26: =(F23-F24)*F20 -> -13230 | G26: =(G23-G24)*G20 -> 35640 | H26: =(H23-H24)*H20 -> -63630 | I26: =(I23-I24)*I20 -> 110081.25 | J26: =(J23-J24)*J20 -> 104287.5 | ... N26: =(N23-N24)*N20 -> 115875 | O26: =SUM(C26:N26) -> 759044.25
B27: Sales volume contribution variance (₹) = (Actual qty − Budget qty) × Std contribution | C27: =C22*C25 -> -97200 | D27: =D22*D25 -> 51300 | E27: =E22*E25 -> -27000 | F27: =F22*F25 -> 141750 | G27: =G22*G25 -> 237600 | H27: =H22*H25 -> 28350 | I27: =I22*I25 -> 76950 | J27: =J22*J25 -> 72900 | ... N27: =N22*N25 -> 81000 | O27: =SUM(C27:N27) -> 816750
B28: Sales mix variance = (Actual qty − Total actual qty × Budget mix %) × Std contribution | C28: =(C20-'Actuals & Forecast'!C$10*Assumptions!$D$15)*C25 -> -163093.67 | D28: =(D20-'Actuals & Forecast'!D$10*Assumptions!$D$15)*D25 -> 37287.342 | E28: =(E20-'Actuals & Forecast'!E$10*Assumptions!$D$15)*E25 -> -85511.392 | F28: =(F20-'Actuals & Forecast'!F$10*Assumptions!$D$15)*F25 -> 121995.57 | G28: =(G20-'Actuals & Forecast'!G$10*Assumptions!$D$15)*G25 -> 229260.76 | H28: =(H20-'Actuals & Forecast'!H$10*Assumptions!$D$15)*H25 -> -55657.595 | I28: =(I20-'Actuals & Forecast'!I$10*Assumptions!$D$15)*I25 -> 0 | J28: =(J20-'Actuals & Forecast'!J$10*Assumptions!$D$15)*J25 -> 0 | ... N28: =(N20-'Actuals & Forecast'!N$10*Assumptions!$D$15)*N25 -> 0 | O28: =SUM(C28:N28) -> 84281.013
B29: Sales quantity variance = (Total actual qty × Budget mix % − Budget qty) × Std contribution | C29: =('Actuals & Forecast'!C$10*Assumptions!$D$15-C21)*C25 -> 65893.671 | D29: =('Actuals & Forecast'!D$10*Assumptions!$D$15-D21)*D25 -> 14012.658 | E29: =('Actuals & Forecast'!E$10*Assumptions!$D$15-E21)*E25 -> 58511.392 | F29: =('Actuals & Forecast'!F$10*Assumptions!$D$15-F21)*F25 -> 19754.43 | G29: =('Actuals & Forecast'!G$10*Assumptions!$D$15-G21)*G25 -> 8339.2405 | H29: =('Actuals & Forecast'!H$10*Assumptions!$D$15-H21)*H25 -> 84007.595 | I29: =('Actuals & Forecast'!I$10*Assumptions!$D$15-I21)*I25 -> 76950 | J29: =('Actuals & Forecast'!J$10*Assumptions!$D$15-J21)*J25 -> 72900 | ... N29: =('Actuals & Forecast'!N$10*Assumptions!$D$15-N21)*N25 -> 81000 | O29: =SUM(C29:N29) -> 732468.99
B30: Total sales variance (₹) = Price variance + Volume variance | C30: =C26+C27 -> -174960 | D30: =D26+D27 -> 121068 | E30: =E26+E27 -> 91800 | F30: =F26+F27 -> 128520 | G30: =G26+G27 -> 273240 | H30: =H26+H27 -> -35280 | I30: =I26+I27 -> 187031.25 | J30: =J26+J27 -> 177187.5 | ... N30: =N26+N27 -> 196875 | O30: =SUM(C30:N30) -> 1575794.2
B32: Gamma
B33: Actual volume (units) | C33: ='Actuals & Forecast'!C9 -> 3713 | D33: ='Actuals & Forecast'!D9 -> 3741 | E33: ='Actuals & Forecast'!E9 -> 3638 | F33: ='Actuals & Forecast'!F9 -> 3662 | G33: ='Actuals & Forecast'!G9 -> 4208 | H33: ='Actuals & Forecast'!H9 -> 4174 | I33: ='Actuals & Forecast'!I9 -> 3669.375 | J33: ='Actuals & Forecast'!J9 -> 3476.25 | ... N33: ='Actuals & Forecast'!N9 -> 3862.5 | O33: =SUM(C33:N33) -> 46117.875
B34: Budget volume (units) | C34: ='Rolling Budget'!C9 -> 3375 | D34: ='Rolling Budget'!D9 -> 3562.5 | E34: ='Rolling Budget'!E9 -> 3750 | F34: ='Rolling Budget'!F9 -> 3937.5 | G34: ='Rolling Budget'!G9 -> 4125 | H34: ='Rolling Budget'!H9 -> 3937.5 | I34: ='Rolling Budget'!I9 -> 3562.5 | J34: ='Rolling Budget'!J9 -> 3375 | ... N34: ='Rolling Budget'!N9 -> 3750 | O34: =SUM(C34:N34) -> 45000
B35: Volume difference (units) | C35: =C33-C34 -> 338 | D35: =D33-D34 -> 178.5 | E35: =E33-E34 -> -112 | F35: =F33-F34 -> -275.5 | G35: =G33-G34 -> 83 | H35: =H33-H34 -> 236.5 | I35: =I33-I34 -> 106.875 | J35: =J33-J34 -> 101.25 | ... N35: =N33-N34 -> 112.5 | O35: =SUM(C35:N35) -> 1117.875
B36: Achieved price (₹ / unit) | C36: ='Actuals & Forecast'!C15 -> 2150 | D36: ='Actuals & Forecast'!D15 -> 2120 | E36: ='Actuals & Forecast'!E15 -> 2085 | F36: ='Actuals & Forecast'!F15 -> 2110 | G36: ='Actuals & Forecast'!G15 -> 2160 | H36: ='Actuals & Forecast'!H15 -> 2135 | I36: ='Actuals & Forecast'!I15 -> 2131.5 | J36: ='Actuals & Forecast'!J15 -> 2131.5 | ... N36: ='Actuals & Forecast'!N15 -> 2131.5 | O36: =IFERROR(O39/O33+O37,0) -> 2129.5985
B37: Budget price (₹ / unit) | C37: =Assumptions!$E$6 -> 2100 | D37: =Assumptions!$E$6 -> 2100 | E37: =Assumptions!$E$6 -> 2100 | F37: =Assumptions!$E$6 -> 2100 | G37: =Assumptions!$E$6 -> 2100 | H37: =Assumptions!$E$6 -> 2100 | I37: =Assumptions!$E$6 -> 2100 | J37: =Assumptions!$E$6 -> 2100 | ... O37: =Assumptions!$E$6 -> 2100
B38: Standard contribution (₹ / unit) | C38: =Assumptions!$E$13 -> 776 | D38: =Assumptions!$E$13 -> 776 | E38: =Assumptions!$E$13 -> 776 | F38: =Assumptions!$E$13 -> 776 | G38: =Assumptions!$E$13 -> 776 | H38: =Assumptions!$E$13 -> 776 | I38: =Assumptions!$E$13 -> 776 | J38: =Assumptions!$E$13 -> 776 | ... O38: =Assumptions!$E$13 -> 776
B39: Sales price variance (₹) = (Actual price − Budget price) × Actual qty | C39: =(C36-C37)*C33 -> 185650 | D39: =(D36-D37)*D33 -> 74820 | E39: =(E36-E37)*E33 -> -54570 | F39: =(F36-F37)*F33 -> 36620 | G39: =(G36-G37)*G33 -> 252480 | H39: =(H36-H37)*H33 -> 146090 | I39: =(I36-I37)*I33 -> 115585.31 | J39: =(J36-J37)*J33 -> 109501.88 | ... N39: =(N36-N37)*N33 -> 121668.75 | O39: =SUM(C39:N39) -> 1365019.1
B40: Sales volume contribution variance (₹) = (Actual qty − Budget qty) × Std contribution | C40: =C35*C38 -> 262288 | D40: =D35*D38 -> 138516 | E40: =E35*E38 -> -86912 | F40: =F35*F38 -> -213788 | G40: =G35*G38 -> 64408 | H40: =H35*H38 -> 183524 | I40: =I35*I38 -> 82935 | J40: =J35*J38 -> 78570 | ... N40: =N35*N38 -> 87300 | O40: =SUM(C40:N40) -> 867471
B41: Sales mix variance = (Actual qty − Total actual qty × Budget mix %) × Std contribution | C41: =(C33-'Actuals & Forecast'!C$10*Assumptions!$E$15)*C38 -> 191269.27 | D41: =(D33-'Actuals & Forecast'!D$10*Assumptions!$E$15)*D38 -> 123413.47 | E41: =(E33-'Actuals & Forecast'!E$10*Assumptions!$E$15)*E38 -> -149974.28 | F41: =(F33-'Actuals & Forecast'!F$10*Assumptions!$E$15)*F38 -> -235078.89 | G41: =(G33-'Actuals & Forecast'!G$10*Assumptions!$E$15)*G38 -> 55420.152 | H41: =(H33-'Actuals & Forecast'!H$10*Assumptions!$E$15)*H38 -> 92982.481 | I41: =(I33-'Actuals & Forecast'!I$10*Assumptions!$E$15)*I38 -> -3.5288394e-10 | J41: =(J33-'Actuals & Forecast'!J$10*Assumptions!$E$15)*J38 -> -3.5288394e-10 | ... N41: =(N33-'Actuals & Forecast'!N$10*Assumptions!$E$15)*N38 -> -3.5288394e-10 | O41: =SUM(C41:N41) -> 78032.203
B42: Sales quantity variance = (Total actual qty × Budget mix % − Budget qty) × Std contribution | C42: =('Actuals & Forecast'!C$10*Assumptions!$E$15-C34)*C38 -> 71018.734 | D42: =('Actuals & Forecast'!D$10*Assumptions!$E$15-D34)*D38 -> 15102.532 | E42: =('Actuals & Forecast'!E$10*Assumptions!$E$15-E34)*E38 -> 63062.278 | F42: =('Actuals & Forecast'!F$10*Assumptions!$E$15-F34)*F38 -> 21290.886 | G42: =('Actuals & Forecast'!G$10*Assumptions!$E$15-G34)*G38 -> 8987.8481 | H42: =('Actuals & Forecast'!H$10*Assumptions!$E$15-H34)*H38 -> 90541.519 | I42: =('Actuals & Forecast'!I$10*Assumptions!$E$15-I34)*I38 -> 82935 | J42: =('Actuals & Forecast'!J$10*Assumptions!$E$15-J34)*J38 -> 78570 | ... N42: =('Actuals & Forecast'!N$10*Assumptions!$E$15-N34)*N38 -> 87300 | O42: =SUM(C42:N42) -> 789438.8
B43: Total sales variance (₹) = Price variance + Volume variance | C43: =C39+C40 -> 447938 | D43: =D39+D40 -> 213336 | E43: =E39+E40 -> -141482 | F43: =F39+F40 -> -177168 | G43: =G39+G40 -> 316888 | H43: =H39+H40 -> 329614 | I43: =I39+I40 -> 198520.31 | J43: =J39+J40 -> 188071.88 | ... N43: =N39+N40 -> 208968.75 | O43: =SUM(C43:N43) -> 2232490.1
B45: Total Sales Variances — All Products
B46: Sales price variance (₹) = Alpha + Beta + Gamma | C46: =C13+C26+C39 -> 220210 | D46: =D13+D26+D39 -> 191138 | E46: =E13+E26+E39 -> 11230 | F46: =F13+F26+F39 -> 235490 | G46: =G13+G26+G39 -> 371720 | H46: =H13+H26+H39 -> 255500 | I46: =I13+I26+I39 -> 350425.31 | J46: =J13+J26+J39 -> 331981.87 | ... N46: =N13+N26+N39 -> 368868.75 | O46: =SUM(C46:N46) -> 3480057.1
B47: Sales volume contribution variance (₹) = Alpha + Beta + Gamma | C47: =C14+C27+C40 -> 287488 | D47: =D14+D27+D40 -> 125216 | E47: =E14+E27+E40 -> 90088 | F47: =F14+F27+F40 -> -36338 | G47: =G14+G27+G40 -> 115008 | H47: =H14+H27+H40 -> 318974 | I47: =I14+I27+I40 -> 256785 | J47: =J14+J27+J40 -> 243270 | ... N47: =N14+N27+N40 -> 270300 | O47: =SUM(C47:N47) -> 2508721
B48: Sales mix variance = Alpha + Beta + Gamma | C48: =C15+C28+C41 -> 67598.38 | D48: =D15+D28+D41 -> 78455.241 | E48: =E15+E28+E41 -> -105166.68 | F48: =F15+F28+F41 -> -102259.27 | G48: =G15+G28+G41 -> 87179.646 | H48: =H15+H28+H41 -> 38637.544 | I48: =I15+I28+I41 -> -3.5288394e-10 | J48: =J15+J28+J41 -> -3.5288394e-10 | ... N48: =N15+N28+N41 -> -3.5288394e-10 | O48: =SUM(C48:N48) -> 64444.861
B49: Sales quantity variance = Alpha + Beta + Gamma | C49: =C16+C29+C42 -> 219889.62 | D49: =D16+D29+D42 -> 46760.759 | E49: =E16+E29+E42 -> 195254.68 | F49: =F16+F29+F42 -> 65921.266 | G49: =G16+G29+G42 -> 27828.354 | H49: =H16+H29+H42 -> 280336.46 | I49: =I16+I29+I42 -> 256785 | J49: =J16+J29+J42 -> 243270 | ... N49: =N16+N29+N42 -> 270300 | O49: =SUM(C49:N49) -> 2444276.1
B50: Total sales variance (₹) = Total price variance + Total volume variance | C50: =C46+C47 -> 507698 | D50: =D46+D47 -> 316354 | E50: =E46+E47 -> 101318 | F50: =F46+F47 -> 199152 | G50: =G46+G47 -> 486728 | H50: =H46+H47 -> 574474 | I50: =I46+I47 -> 607210.31 | J50: =J46+J47 -> 575251.87 | ... N50: =N46+N47 -> 639168.75 | O50: =SUM(C50:N50) -> 5988778.1
B51: Favourable (F) / Unfavourable (U) | C51: =IF(C50>0,"F","U") -> F | D51: =IF(D50>0,"F","U") -> F | E51: =IF(E50>0,"F","U") -> F | F51: =IF(F50>0,"F","U") -> F | G51: =IF(G50>0,"F","U") -> F | H51: =IF(H50>0,"F","U") -> F | I51: =IF(I50>0,"F","U") -> F | J51: =IF(J50>0,"F","U") -> F | ... O51: =IF(O50>0,"F","U") -> F
B53: RECONCILIATION CHECKS (all should be nil)
B54: Alpha - mix + quantity = volume contribution variance | C54: =ROUND(C15+C16-C14,2) -> 0 | D54: =ROUND(D15+D16-D14,2) -> 0 | E54: =ROUND(E15+E16-E14,2) -> 0 | F54: =ROUND(F15+F16-F14,2) -> 0 | G54: =ROUND(G15+G16-G14,2) -> 0 | H54: =ROUND(H15+H16-H14,2) -> 0 | I54: =ROUND(I15+I16-I14,2) -> 0 | J54: =ROUND(J15+J16-J14,2) -> 0 | ... O54: =ROUND(O15+O16-O14,2) -> 0
B55: Beta - mix + quantity = volume contribution variance | C55: =ROUND(C28+C29-C27,2) -> 0 | D55: =ROUND(D28+D29-D27,2) -> 0 | E55: =ROUND(E28+E29-E27,2) -> 0 | F55: =ROUND(F28+F29-F27,2) -> 0 | G55: =ROUND(G28+G29-G27,2) -> 0 | H55: =ROUND(H28+H29-H27,2) -> 0 | I55: =ROUND(I28+I29-I27,2) -> 0 | J55: =ROUND(J28+J29-J27,2) -> 0 | ... O55: =ROUND(O28+O29-O27,2) -> 0
B56: Gamma - mix + quantity = volume contribution variance | C56: =ROUND(C41+C42-C40,2) -> 0 | D56: =ROUND(D41+D42-D40,2) -> 0 | E56: =ROUND(E41+E42-E40,2) -> 0 | F56: =ROUND(F41+F42-F40,2) -> 0 | G56: =ROUND(G41+G42-G40,2) -> 0 | H56: =ROUND(H41+H42-H40,2) -> 0 | I56: =ROUND(I41+I42-I40,2) -> 0 | J56: =ROUND(J41+J42-J40,2) -> 0 | ... O56: =ROUND(O41+O42-O40,2) -> 0
B57: Total - mix + quantity = volume contribution variance | C57: =ROUND(C48+C49-C47,2) -> 0 | D57: =ROUND(D48+D49-D47,2) -> 0 | E57: =ROUND(E48+E49-E47,2) -> 0 | F57: =ROUND(F48+F49-F47,2) -> 0 | G57: =ROUND(G48+G49-G47,2) -> 0 | H57: =ROUND(H48+H49-H47,2) -> 0 | I57: =ROUND(I48+I49-I47,2) -> 0 | J57: =ROUND(J48+J49-J47,2) -> 0 | ... O57: =ROUND(O48+O49-O47,2) -> 0
B58: Total - price + volume = total sales variance | C58: =ROUND(C46+C47-C50,2) -> 0 | D58: =ROUND(D46+D47-D50,2) -> 0 | E58: =ROUND(E46+E47-E50,2) -> 0 | F58: =ROUND(F46+F47-F50,2) -> 0 | G58: =ROUND(G46+G47-G50,2) -> 0 | H58: =ROUND(H46+H47-H50,2) -> 0 | I58: =ROUND(I46+I47-I50,2) -> 0 | J58: =ROUND(J46+J47-J50,2) -> 0 | ... O58: =ROUND(O46+O47-O50,2) -> 0
B59: Status | C59: {=IF(SUMPRODUCT(ABS(C54:C58))=0,"OK","ERROR")} -> OK | D59: {=IF(SUMPRODUCT(ABS(D54:D58))=0,"OK","ERROR")} -> OK | E59: {=IF(SUMPRODUCT(ABS(E54:E58))=0,"OK","ERROR")} -> OK | F59: {=IF(SUMPRODUCT(ABS(F54:F58))=0,"OK","ERROR")} -> OK | G59: {=IF(SUMPRODUCT(ABS(G54:G58))=0,"OK","ERROR")} -> OK | H59: {=IF(SUMPRODUCT(ABS(H54:H58))=0,"OK","ERROR")} -> OK | I59: {=IF(SUMPRODUCT(ABS(I54:I58))=0,"OK","ERROR")} -> OK | J59: {=IF(SUMPRODUCT(ABS(J54:J58))=0,"OK","ERROR")} -> OK | ... O59: {=IF(SUMPRODUCT(ABS(O54:O58))=0,"OK","ERROR")} -> OK

Sheet Overhead Variances
B1: Cost & Overhead Variance Analysis
B3: Month | C3: =DATE(2026,4,1) -> 46113 | D3: =EDATE(C3,1) -> 46143 | E3: =EDATE(D3,1) -> 46174 | F3: =EDATE(E3,1) -> 46204 | G3: =EDATE(F3,1) -> 46235 | H3: =EDATE(G3,1) -> 46266 | I3: =EDATE(H3,1) -> 46296 | J3: =EDATE(I3,1) -> 46327 | K3: =EDATE(J3,1) -> 46357 | ... N3: =EDATE(M3,1) -> 46447 | O3: FY Total
B4: Actual / Forecast | C4: Actual | D4: Actual | E4: Actual | F4: Actual | G4: Actual | H4: Actual | I4: Forecast | J4: Forecast | K4: Forecast | L4: Forecast | M4: Forecast | N4: Forecast
B6: Operating Data
B7: Standard hours for actual output | C7: ='Actuals & Forecast'!C26 -> 13282.8 | D7: ='Actuals & Forecast'!D26 -> 13795.4 | E7: ='Actuals & Forecast'!E26 -> 14417.6 | F7: ='Actuals & Forecast'!F26 -> 14988.9 | G7: ='Actuals & Forecast'!G26 -> 15977 | H7: ='Actuals & Forecast'!H26 -> 15506.7 | I7: ='Actuals & Forecast'!I26 -> 13992.55 | J7: ='Actuals & Forecast'!J26 -> 13256.1 | ... N7: ='Actuals & Forecast'!N26 -> 14729 | O7: =SUM(C7:N7) -> 175605.95
B8: Actual labour hours | C8: ='Actuals & Forecast'!C24 -> 13681 | D8: ='Actuals & Forecast'!D24 -> 13933 | E8: ='Actuals & Forecast'!E24 -> 15138 | F8: ='Actuals & Forecast'!F24 -> 14839 | G8: ='Actuals & Forecast'!G24 -> 16297 | H8: ='Actuals & Forecast'!H24 -> 16127 | I8: ='Actuals & Forecast'!I24 -> 14272.401 | J8: ='Actuals & Forecast'!J24 -> 13521.222 | ... N8: ='Actuals & Forecast'!N24 -> 15023.58 | O8: =SUM(C8:N8) -> 179405.3
B9: Budgeted labour hours | C9: ='Rolling Budget'!C18 -> 12870 | D9: ='Rolling Budget'!D18 -> 13585 | E9: ='Rolling Budget'!E18 -> 14300 | F9: ='Rolling Budget'!F18 -> 15015 | G9: ='Rolling Budget'!G18 -> 15730 | H9: ='Rolling Budget'!H18 -> 15015 | I9: ='Rolling Budget'!I18 -> 13585 | J9: ='Rolling Budget'!J18 -> 12870 | ... N9: ='Rolling Budget'!N18 -> 14300 | O9: =SUM(C9:N9) -> 171600
B10: Standard variable OH rate (₹ / hour) | C10: =Assumptions!$C$32 -> 120 | D10: =Assumptions!$C$32 -> 120 | E10: =Assumptions!$C$32 -> 120 | F10: =Assumptions!$C$32 -> 120 | G10: =Assumptions!$C$32 -> 120 | H10: =Assumptions!$C$32 -> 120 | I10: =Assumptions!$C$32 -> 120 | J10: =Assumptions!$C$32 -> 120 | ... O10: =Assumptions!$C$32 -> 120
B11: Standard fixed OH rate (₹ / hour) | C11: =Assumptions!$C$31 -> 454.54545 | D11: =Assumptions!$C$31 -> 454.54545 | E11: =Assumptions!$C$31 -> 454.54545 | F11: =Assumptions!$C$31 -> 454.54545 | G11: =Assumptions!$C$31 -> 454.54545 | H11: =Assumptions!$C$31 -> 454.54545 | I11: =Assumptions!$C$31 -> 454.54545 | J11: =Assumptions!$C$31 -> 454.54545 | ... O11: =Assumptions!$C$31 -> 454.54545
B13: Direct Material Variance
B14: Standard material cost for actual output = Actual volume × Std material cost | C14: ='Actuals & Forecast'!C7*Assumptions!$C$7+'Actuals & Forecast'!C8*Assumptions!$D$7+'Actuals & Forecast'!C9*Assumptions!$E$7 -> 8528180 | D14: ='Actuals & Forecast'!D7*Assumptions!$C$7+'Actuals & Forecast'!D8*Assumptions!$D$7+'Actuals & Forecast'!D9*Assumptions!$E$7 -> 8837540 | E14: ='Actuals & Forecast'!E7*Assumptions!$C$7+'Actuals & Forecast'!E8*Assumptions!$D$7+'Actuals & Forecast'!E9*Assumptions!$E$7 -> 9226360 | F14: ='Actuals & Forecast'!F7*Assumptions!$C$7+'Actuals & Forecast'!F8*Assumptions!$D$7+'Actuals & Forecast'!F9*Assumptions!$E$7 -> 9571640 | G14: ='Actuals & Forecast'!G7*Assumptions!$C$7+'Actuals & Forecast'!G8*Assumptions!$D$7+'Actuals & Forecast'!G9*Assumptions!$E$7 -> 10216000 | H14: ='Actuals & Forecast'!H7*Assumptions!$C$7+'Actuals & Forecast'!H8*Assumptions!$D$7+'Actuals & Forecast'!H9*Assumptions!$E$7 -> 9937720 | I14: ='Actuals & Forecast'!I7*Assumptions!$C$7+'Actuals & Forecast'!I8*Assumptions!$D$7+'Actuals & Forecast'!I9*Assumptions!$E$7 -> 8958167.5 | J14: ='Actuals & Forecast'!J7*Assumptions!$C$7+'Actuals & Forecast'!J8*Assumptions!$D$7+'Actuals & Forecast'!J9*Assumptions!$E$7 -> 8486685 | ... N14: ='Actuals & Forecast'!N7*Assumptions!$C$7+'Actuals & Forecast'!N8*Assumptions!$D$7+'Actuals & Forecast'!N9*Assumptions!$E$7 -> 9429650 | O14: =SUM(C14:N14) -> 1.1242386e+08
B15: Actual material cost | C15: ='Actuals & Forecast'!C43 -> 8699000 | D15: ='Actuals & Forecast'!D43 -> 8838000 | E15: ='Actuals & Forecast'!E43 -> 9595000 | F15: ='Actuals & Forecast'!F43 -> 9667000 | G15: ='Actuals & Forecast'!G43 -> 10114000 | H15: ='Actuals & Forecast'!H43 -> 10236000 | I15: ='Actuals & Forecast'!I43 -> 9456241.6 | J15: ='Actuals & Forecast'!J43 -> 8958544.7 | ... N15: ='Actuals & Forecast'!N43 -> 9953938.5 | O15: =SUM(C15:N15) -> 1.1637493e+08
B16: Total direct material variance = Std material cost for actual output − Actual material cost | C16: =C14-C15 -> -170820 | D16: =D14-D15 -> -460 | E16: =E14-E15 -> -368640 | F16: =F14-F15 -> -95360 | G16: =G14-G15 -> 102000 | H16: =H14-H15 -> -298280 | I16: =I14-I15 -> -498074.11 | J16: =J14-J15 -> -471859.69 | ... N16: =N14-N15 -> -524288.54 | O16: =SUM(C16:N16) -> -3951076.8
B18: Direct Labour Variances
B19: Standard labour cost for actual output | C19: ='Actuals & Forecast'!C7*Assumptions!$C$10+'Actuals & Forecast'!C8*Assumptions!$D$10+'Actuals & Forecast'!C9*Assumptions!$E$10 -> 3714696 | D19: ='Actuals & Forecast'!D7*Assumptions!$C$10+'Actuals & Forecast'!D8*Assumptions!$D$10+'Actuals & Forecast'!D9*Assumptions!$E$10 -> 3859396 | E19: ='Actuals & Forecast'!E7*Assumptions!$C$10+'Actuals & Forecast'!E8*Assumptions!$D$10+'Actuals & Forecast'!E9*Assumptions!$E$10 -> 4018240 | F19: ='Actuals & Forecast'!F7*Assumptions!$C$10+'Actuals & Forecast'!F8*Assumptions!$D$10+'Actuals & Forecast'!F9*Assumptions!$E$10 -> 4178730 | G19: ='Actuals & Forecast'!G7*Assumptions!$C$10+'Actuals & Forecast'!G8*Assumptions!$D$10+'Actuals & Forecast'!G9*Assumptions!$E$10 -> 4470052 | H19: ='Actuals & Forecast'!H7*Assumptions!$C$10+'Actuals & Forecast'!H8*Assumptions!$D$10+'Actuals & Forecast'!H9*Assumptions!$E$10 -> 4333902 | I19: ='Actuals & Forecast'!I7*Assumptions!$C$10+'Actuals & Forecast'!I8*Assumptions!$D$10+'Actuals & Forecast'!I9*Assumptions!$E$10 -> 3908129 | J19: ='Actuals & Forecast'!J7*Assumptions!$C$10+'Actuals & Forecast'!J8*Assumptions!$D$10+'Actuals & Forecast'!J9*Assumptions!$E$10 -> 3702438 | ... N19: ='Actuals & Forecast'!N7*Assumptions!$C$10+'Actuals & Forecast'!N8*Assumptions!$D$10+'Actuals & Forecast'!N9*Assumptions!$E$10 -> 4113820 | O19: =SUM(C19:N19) -> 49052245
B20: Actual labour cost | C20: ='Actuals & Forecast'!C44 -> 3666508 | D20: ='Actuals & Forecast'!D44 -> 3817642 | E20: ='Actuals & Forecast'!E44 -> 4102398 | F20: ='Actuals & Forecast'!F44 -> 4140081 | G20: ='Actuals & Forecast'!G44 -> 4497972 | H20: ='Actuals & Forecast'!H44 -> 4402671 | I20: ='Actuals & Forecast'!I44 -> 4185606.2 | J20: ='Actuals & Forecast'!J44 -> 3965311.1 | ... N20: ='Actuals & Forecast'!N44 -> 4405901.2 | O20: =SUM(C20:N20) -> 50842384
B21: Standard labour rate for actual mix (₹ / hour) | C21: =IFERROR(C19/C7,0) -> 279.66212 | D21: =IFERROR(D19/D7,0) -> 279.75963 | E21: =IFERROR(E19/E7,0) -> 278.70381 | F21: =IFERROR(F19/F7,0) -> 278.7883 | G21: =IFERROR(G19/G7,0) -> 279.78043 | H21: =IFERROR(H19/H7,0) -> 279.48577 | I21: =IFERROR(I19/I7,0) -> 279.3007 | J21: =IFERROR(J19/J7,0) -> 279.3007 | ... O21: =IFERROR(O19/O7,0) -> 279.33134
B22: Labour rate variance = (Std rate − Actual rate) × Actual hours | C22: =(C21-'Actuals & Forecast'!C25)*C8 -> 159549.46 | D22: =(D21-'Actuals & Forecast'!D25)*D8 -> 80248.925 | E22: =(E21-'Actuals & Forecast'!E25)*E8 -> 116620.22 | F22: =(F21-'Actuals & Forecast'!F25)*F8 -> -3141.3667 | G22: =(G21-'Actuals & Forecast'!G25)*G8 -> 61609.739 | H22: =(H21-'Actuals & Forecast'!H25)*H8 -> 104596.02 | I22: =(I21-'Actuals & Forecast'!I25)*I8 -> -199314.58 | J22: =(J21-'Actuals & Forecast'!J25)*J8 -> -188824.34 | ... N22: =(N21-'Actuals & Forecast'!N25)*N8 -> -209804.82 | O22: =SUM(C22:N22) -> -728855.68
B23: Labour efficiency variance = (Std hours − Actual hours) × Std rate | C23: =(C7-C8)*C21 -> -111361.46 | D23: =(D7-D8)*D21 -> -38494.925 | E23: =(E7-E8)*E21 -> -200778.22 | F23: =(F7-F8)*F21 -> 41790.367 | G23: =(G7-G8)*G21 -> -89529.739 | H23: =(H7-H8)*H21 -> -173365.02 | I23: =(I7-I8)*I21 -> -78162.58 | J23: =(J7-J8)*J21 -> -74048.76 | ... N23: =(N7-N8)*N21 -> -82276.4 | O23: =SUM(C23:N23) -> -1061283.6
B24: Total direct labour variance = Rate variance + Efficiency variance | C24: =C22+C23 -> 48188 | D24: =D22+D23 -> 41754 | E24: =E22+E23 -> -84158 | F24: =F22+F23 -> 38649 | G24: =G22+G23 -> -27920 | H24: =H22+H23 -> -68769 | I24: =I22+I23 -> -277477.16 | J24: =J22+J23 -> -262873.1 | ... N24: =N22+N23 -> -292081.22 | O24: =SUM(C24:N24) -> -1790139.3
B25: Check (should be nil) | C25: =ROUND(C24-(C19-C20),2) -> 0 | D25: =ROUND(D24-(D19-D20),2) -> 0 | E25: =ROUND(E24-(E19-E20),2) -> 0 | F25: =ROUND(F24-(F19-F20),2) -> 0 | G25: =ROUND(G24-(G19-G20),2) -> 0 | H25: =ROUND(H24-(H19-H20),2) -> 0 | I25: =ROUND(I24-(I19-I20),2) -> 0 | J25: =ROUND(J24-(J19-J20),2) -> 0 | ... N25: =ROUND(N24-(N19-N20),2) -> 0 | O25: =SUM(C25:N25) -> 0
B27: Variable Overhead Variances
B28: Standard variable OH on standard hours for actual output | C28: =C7*C10 -> 1593936 | D28: =D7*D10 -> 1655448 | E28: =E7*E10 -> 1730112 | F28: =F7*F10 -> 1798668 | G28: =G7*G10 -> 1917240 | H28: =H7*H10 -> 1860804 | I28: =I7*I10 -> 1679106 | J28: =J7*J10 -> 1590732 | ... N28: =N7*N10 -> 1767480 | O28: =SUM(C28:N28) -> 21072714
B29: Standard variable OH on actual hours | C29: =C8*C10 -> 1641720 | D29: =D8*D10 -> 1671960 | E29: =E8*E10 -> 1816560 | F29: =F8*F10 -> 1780680 | G29: =G8*G10 -> 1955640 | H29: =H8*H10 -> 1935240 | I29: =I8*I10 -> 1712688.1 | J29: =J8*J10 -> 1622546.6 | ... N29: =N8*N10 -> 1802829.6 | O29: =SUM(C29:N29) -> 21528636
B30: Actual variable OH cost | C30: ='Actuals & Forecast'!C33 -> 1667000 | D30: ='Actuals & Forecast'!D33 -> 1693000 | E30: ='Actuals & Forecast'!E33 -> 1859000 | F30: ='Actuals & Forecast'!F33 -> 1791000 | G30: ='Actuals & Forecast'!G33 -> 1984000 | H30: ='Actuals & Forecast'!H33 -> 1996000 | I30: ='Actuals & Forecast'!I33 -> 1764068.8 | J30: ='Actuals & Forecast'!J33 -> 1671223 | ... N30: ='Actuals & Forecast'!N33 -> 1856914.5 | O30: =SUM(C30:N30) -> 22038641
B31: Variable OH expenditure (spending) variance = (Actual hours × Std VOH rate) − Actual VOH | C31: =C29-C30 -> -25280 | D31: =D29-D30 -> -21040 | E31: =E29-E30 -> -42440 | F31: =F29-F30 -> -10320 | G31: =G29-G30 -> -28360 | H31: =H29-H30 -> -60760 | I31: =I29-I30 -> -51380.644 | J31: =J29-J30 -> -48676.399 | ... N31: =N29-N30 -> -54084.888 | O31: =SUM(C31:N31) -> -510005.08
B32: Variable OH efficiency variance = (Std hours − Actual hours) × Std VOH rate | C32: =(C7-C8)*C10 -> -47784 | D32: =(D7-D8)*D10 -> -16512 | E32: =(E7-E8)*E10 -> -86448 | F32: =(F7-F8)*F10 -> 17988 | G32: =(G7-G8)*G10 -> -38400 | H32: =(H7-H8)*H10 -> -74436 | I32: =(I7-I8)*I10 -> -33582.12 | J32: =(J7-J8)*J10 -> -31814.64 | ... N32: =(N7-N8)*N10 -> -35349.6 | O32: =SUM(C32:N32) -> -455922.12
B33: Total variable overhead variance = Spending variance + Efficiency variance | C33: =C31+C32 -> -73064 | D33: =D31+D32 -> -37552 | E33: =E31+E32 -> -128888 | F33: =F31+F32 -> 7668 | G33: =G31+G32 -> -66760 | H33: =H31+H32 -> -135196 | I33: =I31+I32 -> -84962.764 | J33: =J31+J32 -> -80491.039 | ... N33: =N31+N32 -> -89434.488 | O33: =SUM(C33:N33) -> -965927.2
B34: Variable OH spending variance by department
B35: Machining = Actual hours × Std dept VOH rate − Actual dept VOH | C35: =C$8*Assumptions!$D$24-'Actuals & Forecast'!C29 -> -24140 | D35: =D$8*Assumptions!$D$24-'Actuals & Forecast'!D29 -> -8020 | E35: =E$8*Assumptions!$D$24-'Actuals & Forecast'!E29 -> -36720 | F35: =F$8*Assumptions!$D$24-'Actuals & Forecast'!F29 -> 9340 | G35: =G$8*Assumptions!$D$24-'Actuals & Forecast'!G29 -> -19180 | H35: =H$8*Assumptions!$D$24-'Actuals & Forecast'!H29 -> -48380 | I35: =I$8*Assumptions!$D$24-'Actuals & Forecast'!I29 -> -25690.322 | J35: =J$8*Assumptions!$D$24-'Actuals & Forecast'!J29 -> -24338.2 | ... N35: =N$8*Assumptions!$D$24-'Actuals & Forecast'!N29 -> -27042.444 | O35: =SUM(C35:N35) -> -288002.54
B36: Assembly = Actual hours × Std dept VOH rate − Actual dept VOH | C36: =C$8*Assumptions!$D$25-'Actuals & Forecast'!C30 -> 9835 | D36: =D$8*Assumptions!$D$25-'Actuals & Forecast'!D30 -> -9345 | E36: =E$8*Assumptions!$D$25-'Actuals & Forecast'!E30 -> -5170 | F36: =F$8*Assumptions!$D$25-'Actuals & Forecast'!F30 -> -15635 | G36: =G$8*Assumptions!$D$25-'Actuals & Forecast'!G30 -> 5395 | H36: =H$8*Assumptions!$D$25-'Actuals & Forecast'!H30 -> -11555 | I36: =I$8*Assumptions!$D$25-'Actuals & Forecast'!I30 -> -14986.021 | J36: =J$8*Assumptions!$D$25-'Actuals & Forecast'!J30 -> -14197.283 | ... N36: =N$8*Assumptions!$D$25-'Actuals & Forecast'!N30 -> -15774.759 | O36: =SUM(C36:N36) -> -120334.82
B37: Packing = Actual hours × Std dept VOH rate − Actual dept VOH | C37: =C$8*Assumptions!$D$26-'Actuals & Forecast'!C31 -> -9785 | D37: =D$8*Assumptions!$D$26-'Actuals & Forecast'!D31 -> -6005 | E37: =E$8*Assumptions!$D$26-'Actuals & Forecast'!E31 -> 2070 | F37: =F$8*Assumptions!$D$26-'Actuals & Forecast'!F31 -> -4415 | G37: =G$8*Assumptions!$D$26-'Actuals & Forecast'!G31 -> -9545 | H37: =H$8*Assumptions!$D$26-'Actuals & Forecast'!H31 -> -2095 | I37: =I$8*Assumptions!$D$26-'Actuals & Forecast'!I31 -> -6422.5805 | J37: =J$8*Assumptions!$D$26-'Actuals & Forecast'!J31 -> -6084.5499 | ... N37: =N$8*Assumptions!$D$26-'Actuals & Forecast'!N31 -> -6760.611 | O37: =SUM(C37:N37) -> -70000.635
B38: Admin & Support = Actual hours × Std dept VOH rate − Actual dept VOH | C38: =C$8*Assumptions!$D$27-'Actuals & Forecast'!C32 -> -1190 | D38: =D$8*Assumptions!$D$27-'Actuals & Forecast'!D32 -> 2330 | E38: =E$8*Assumptions!$D$27-'Actuals & Forecast'!E32 -> -2620 | F38: =F$8*Assumptions!$D$27-'Actuals & Forecast'!F32 -> 390 | G38: =G$8*Assumptions!$D$27-'Actuals & Forecast'!G32 -> -5030 | H38: =H$8*Assumptions!$D$27-'Actuals & Forecast'!H32 -> 1270 | I38: =I$8*Assumptions!$D$27-'Actuals & Forecast'!I32 -> -4281.7203 | J38: =J$8*Assumptions!$D$27-'Actuals & Forecast'!J32 -> -4056.3666 | ... N38: =N$8*Assumptions!$D$27-'Actuals & Forecast'!N32 -> -4507.074 | O38: =SUM(C38:N38) -> -31667.09
B39: Total (check vs spending variance) = Sum of department spending variances | C39: =SUM(C35:C38) -> -25280 | D39: =SUM(D35:D38) -> -21040 | E39: =SUM(E35:E38) -> -42440 | F39: =SUM(F35:F38) -> -10320 | G39: =SUM(G35:G38) -> -28360 | H39: =SUM(H35:H38) -> -60760 | I39: =SUM(I35:I38) -> -51380.644 | J39: =SUM(J35:J38) -> -48676.399 | ... N39: =SUM(N35:N38) -> -54084.888 | O39: =SUM(C39:N39) -> -510005.08
B41: Fixed Overhead Variances
B42: Budgeted fixed overhead | C42: ='Rolling Budget'!C34 -> 6500000 | D42: ='Rolling Budget'!D34 -> 6500000 | E42: ='Rolling Budget'!E34 -> 6500000 | F42: ='Rolling Budget'!F34 -> 6500000 | G42: ='Rolling Budget'!G34 -> 6500000 | H42: ='Rolling Budget'!H34 -> 6500000 | I42: ='Rolling Budget'!I34 -> 6500000 | J42: ='Rolling Budget'!J34 -> 6500000 | ... N42: ='Rolling Budget'!N34 -> 6500000 | O42: =SUM(C42:N42) -> 78000000
B43: Actual fixed overhead | C43: ='Actuals & Forecast'!C40 -> 6573000 | D43: ='Actuals & Forecast'!D40 -> 6506000 | E43: ='Actuals & Forecast'!E40 -> 6600000 | F43: ='Actuals & Forecast'!F40 -> 6556000 | G43: ='Actuals & Forecast'!G40 -> 6611000 | H43: ='Actuals & Forecast'!H40 -> 6582000 | I43: ='Actuals & Forecast'!I40 -> 6662500 | J43: ='Actuals & Forecast'!J40 -> 6662500 | ... N43: ='Actuals & Forecast'!N40 -> 6662500 | O43: =SUM(C43:N43) -> 79403000
B44: Fixed overhead absorbed (std hrs × std rate) | C44: =C7*C11 -> 6037636.4 | D44: =D7*D11 -> 6270636.4 | E44: =E7*E11 -> 6553454.5 | F44: =F7*F11 -> 6813136.4 | G44: =G7*G11 -> 7262272.7 | H44: =H7*H11 -> 7048500 | I44: =I7*I11 -> 6360250 | J44: =J7*J11 -> 6025500 | ... N44: =N7*N11 -> 6695000 | O44: =SUM(C44:N44) -> 79820886
B45: Fixed OH expenditure variance = Budgeted FOH − Actual FOH | C45: =C42-C43 -> -73000 | D45: =D42-D43 -> -6000 | E45: =E42-E43 -> -100000 | F45: =F42-F43 -> -56000 | G45: =G42-G43 -> -111000 | H45: =H42-H43 -> -82000 | I45: =I42-I43 -> -162500 | J45: =J42-J43 -> -162500 | ... N45: =N42-N43 -> -162500 | O45: =SUM(C45:N45) -> -1403000
B46: Fixed OH volume variance = Absorbed FOH − Budgeted FOH | C46: =C44-C42 -> -462363.64 | D46: =D44-D42 -> -229363.64 | E46: =E44-E42 -> 53454.545 | F46: =F44-F42 -> 313136.36 | G46: =G44-G42 -> 762272.73 | H46: =H44-H42 -> 548500 | I46: =I44-I42 -> -139750 | J46: =J44-J42 -> -474500 | ... N46: =N44-N42 -> 195000 | O46: =SUM(C46:N46) -> 1820886.4
B47: Capacity variance = (Actual hours − Budgeted hours) × Std FOH rate | C47: =(C8-C9)*C11 -> 368636.36 | D47: =(D8-D9)*D11 -> 158181.82 | E47: =(E8-E9)*E11 -> 380909.09 | F47: =(F8-F9)*F11 -> -80000 | G47: =(G8-G9)*G11 -> 257727.27 | H47: =(H8-H9)*H11 -> 505454.55 | I47: =(I8-I9)*I11 -> 312455 | J47: =(J8-J9)*J11 -> 296010 | ... N47: =(N8-N9)*N11 -> 328900 | O47: =SUM(C47:N47) -> 3547864.1
B48: Efficiency variance = (Std hours − Actual hours) × Std FOH rate | C48: =(C7-C8)*C11 -> -181000 | D48: =(D7-D8)*D11 -> -62545.455 | E48: =(E7-E8)*E11 -> -327454.55 | F48: =(F7-F8)*F11 -> 68136.364 | G48: =(G7-G8)*G11 -> -145454.55 | H48: =(H7-H8)*H11 -> -281954.55 | I48: =(I7-I8)*I11 -> -127205 | J48: =(J7-J8)*J11 -> -120510 | ... N48: =(N7-N8)*N11 -> -133900 | O48: =SUM(C48:N48) -> -1726977.7
B49: Total fixed overhead variance (absorbed − actual) = Absorbed FOH − Actual FOH | C49: =C44-C43 -> -535363.64 | D49: =D44-D43 -> -235363.64 | E49: =E44-E43 -> -46545.455 | F49: =F44-F43 -> 257136.36 | G49: =G44-G43 -> 651272.73 | H49: =H44-H43 -> 466500 | I49: =I44-I43 -> -302250 | J49: =J44-J43 -> -637000 | ... N49: =N44-N43 -> 32500 | O49: =SUM(C49:N49) -> 417886.36
B50: Fixed OH expenditure variance by department
B51: Machining = Budgeted dept FOH − Actual dept FOH | C51: ='Rolling Budget'!C30-'Actuals & Forecast'!C36 -> -53333.333 | D51: ='Rolling Budget'!D30-'Actuals & Forecast'!D36 -> 26666.667 | E51: ='Rolling Budget'!E30-'Actuals & Forecast'!E36 -> -80333.333 | F51: ='Rolling Budget'!F30-'Actuals & Forecast'!F36 -> -26333.333 | G51: ='Rolling Budget'!G30-'Actuals & Forecast'!G36 -> -106333.33 | H51: ='Rolling Budget'!H30-'Actuals & Forecast'!H36 -> -333.33333 | I51: ='Rolling Budget'!I30-'Actuals & Forecast'!I36 -> -66666.667 | J51: ='Rolling Budget'!J30-'Actuals & Forecast'!J36 -> -66666.667 | ... N51: ='Rolling Budget'!N30-'Actuals & Forecast'!N36 -> -66666.667 | O51: =SUM(C51:N51) -> -640000
B52: Assembly = Budgeted dept FOH − Actual dept FOH | C52: ='Rolling Budget'!C31-'Actuals & Forecast'!C37 -> 17000 | D52: ='Rolling Budget'!D31-'Actuals & Forecast'!D37 -> -18000 | E52: ='Rolling Budget'!E31-'Actuals & Forecast'!E37 -> 0 | F52: ='Rolling Budget'!F31-'Actuals & Forecast'!F37 -> -35000 | G52: ='Rolling Budget'!G31-'Actuals & Forecast'!G37 -> 35000 | H52: ='Rolling Budget'!H31-'Actuals & Forecast'!H37 -> -53000 | I52: ='Rolling Budget'!I31-'Actuals & Forecast'!I37 -> -43750 | J52: ='Rolling Budget'!J31-'Actuals & Forecast'!J37 -> -43750 | ... N52: ='Rolling Budget'!N31-'Actuals & Forecast'!N37 -> -43750 | O52: =SUM(C52:N52) -> -316500
B53: Packing = Budgeted dept FOH − Actual dept FOH | C53: ='Rolling Budget'!C32-'Actuals & Forecast'!C38 -> -23000 | D53: ='Rolling Budget'!D32-'Actuals & Forecast'!D38 -> -15000 | E53: ='Rolling Budget'!E32-'Actuals & Forecast'!E38 -> 7000 | F53: ='Rolling Budget'!F32-'Actuals & Forecast'!F38 -> -8000 | G53: ='Rolling Budget'!G32-'Actuals & Forecast'!G38 -> 0 | H53: ='Rolling Budget'!H32-'Actuals & Forecast'!H38 -> -15000 | I53: ='Rolling Budget'!I32-'Actuals & Forecast'!I38 -> -18750 | J53: ='Rolling Budget'!J32-'Actuals & Forecast'!J38 -> -18750 | ... N53: ='Rolling Budget'!N32-'Actuals & Forecast'!N38 -> -18750 | O53: =SUM(C53:N53) -> -166500
B54: Admin & Support = Budgeted dept FOH − Actual dept FOH | C54: ='Rolling Budget'!C33-'Actuals & Forecast'!C39 -> -13666.667 | D54: ='Rolling Budget'!D33-'Actuals & Forecast'!D39 -> 333.33333 | E54: ='Rolling Budget'!E33-'Actuals & Forecast'!E39 -> -26666.667 | F54: ='Rolling Budget'!F33-'Actuals & Forecast'!F39 -> 13333.333 | G54: ='Rolling Budget'!G33-'Actuals & Forecast'!G39 -> -39666.667 | H54: ='Rolling Budget'!H33-'Actuals & Forecast'!H39 -> -13666.667 | I54: ='Rolling Budget'!I33-'Actuals & Forecast'!I39 -> -33333.333 | J54: ='Rolling Budget'!J33-'Actuals & Forecast'!J39 -> -33333.333 | ... N54: ='Rolling Budget'!N33-'Actuals & Forecast'!N39 -> -33333.333 | O54: =SUM(C54:N54) -> -280000
B55: Total (check vs expenditure variance) = Sum of department expenditure variances | C55: =SUM(C51:C54) -> -73000 | D55: =SUM(D51:D54) -> -6000 | E55: =SUM(E51:E54) -> -100000 | F55: =SUM(F51:F54) -> -56000 | G55: =SUM(G51:G54) -> -111000 | H55: =SUM(H51:H54) -> -82000 | I55: =SUM(I51:I54) -> -162500 | J55: =SUM(J51:J54) -> -162500 | ... N55: =SUM(N51:N54) -> -162500 | O55: =SUM(C55:N55) -> -1403000
B57: Total Overhead Variance
B58: Variable + fixed overhead variance = Total VOH variance + Total FOH variance | C58: =C33+C49 -> -608427.64 | D58: =D33+D49 -> -272915.64 | E58: =E33+E49 -> -175433.45 | F58: =F33+F49 -> 264804.36 | G58: =G33+G49 -> 584512.73 | H58: =H33+H49 -> 331304 | I58: =I33+I49 -> -387212.76 | J58: =J33+J49 -> -717491.04 | ... N58: =N33+N49 -> -56934.488 | O58: =SUM(C58:N58) -> -548040.84
B59: Favourable (F) / Unfavorable (U) | C59: =IF(C58>0,"F","U") -> U | D59: =IF(D58>0,"F","U") -> U | E59: =IF(E58>0,"F","U") -> U | F59: =IF(F58>0,"F","U") -> F | G59: =IF(G58>0,"F","U") -> F | H59: =IF(H58>0,"F","U") -> F | I59: =IF(I58>0,"F","U") -> U | J59: =IF(J58>0,"F","U") -> U | ... O59: =IF(O58>0,"F","U") -> U
B61: Reconciliation Checks (all should be nil)
B62: Labour — rate + efficiency = standard less actual labour cost | C62: =C25 -> 0 | D62: =D25 -> 0 | E62: =E25 -> 0 | F62: =F25 -> 0 | G62: =G25 -> 0 | H62: =H25 -> 0 | I62: =I25 -> 0 | J62: =J25 -> 0 | ... O62: =O25 -> 0
B63: Variable OH — spending + efficiency = total variable OH variance | C63: =ROUND(C31+C32-C33,2) -> 0 | D63: =ROUND(D31+D32-D33,2) -> 0 | E63: =ROUND(E31+E32-E33,2) -> 0 | F63: =ROUND(F31+F32-F33,2) -> 0 | G63: =ROUND(G31+G32-G33,2) -> 0 | H63: =ROUND(H31+H32-H33,2) -> 0 | I63: =ROUND(I31+I32-I33,2) -> 0 | J63: =ROUND(J31+J32-J33,2) -> 0 | ... O63: =ROUND(O31+O32-O33,2) -> 0
B64: Variable OH — department spending variances = total spending variance | C64: =ROUND(C39-C31,2) -> 0 | D64: =ROUND(D39-D31,2) -> 0 | E64: =ROUND(E39-E31,2) -> 0 | F64: =ROUND(F39-F31,2) -> 0 | G64: =ROUND(G39-G31,2) -> 0 | H64: =ROUND(H39-H31,2) -> 0 | I64: =ROUND(I39-I31,2) -> 0 | J64: =ROUND(J39-J31,2) -> 0 | ... O64: =ROUND(O39-O31,2) -> 0
B65: Fixed OH — expenditure + volume = total fixed OH variance | C65: =ROUND(C45+C46-C49,2) -> 0 | D65: =ROUND(D45+D46-D49,2) -> 0 | E65: =ROUND(E45+E46-E49,2) -> 0 | F65: =ROUND(F45+F46-F49,2) -> 0 | G65: =ROUND(G45+G46-G49,2) -> 0 | H65: =ROUND(H45+H46-H49,2) -> 0 | I65: =ROUND(I45+I46-I49,2) -> 0 | J65: =ROUND(J45+J46-J49,2) -> 0 | ... O65: =ROUND(O45+O46-O49,2) -> 0
B66: Fixed OH — capacity + efficiency = absorbed less budgeted hours at std rate | C66: =ROUND(C47+C48-(C44-C9*C11),2) -> 0 | D66: =ROUND(D47+D48-(D44-D9*D11),2) -> 0 | E66: =ROUND(E47+E48-(E44-E9*E11),2) -> 0 | F66: =ROUND(F47+F48-(F44-F9*F11),2) -> 0 | G66: =ROUND(G47+G48-(G44-G9*G11),2) -> 0 | H66: =ROUND(H47+H48-(H44-H9*H11),2) -> 0 | I66: =ROUND(I47+I48-(I44-I9*I11),2) -> 0 | J66: =ROUND(J47+J48-(J44-J9*J11),2) -> 0 | ... O66: =ROUND(O47+O48-(O44-O9*O11),2) -> 0
B67: Fixed OH — department expenditure variances = expenditure variance | C67: =ROUND(C55-C45,2) -> 0 | D67: =ROUND(D55-D45,2) -> 0 | E67: =ROUND(E55-E45,2) -> 0 | F67: =ROUND(F55-F45,2) -> 0 | G67: =ROUND(G55-G45,2) -> 0 | H67: =ROUND(H55-H45,2) -> 0 | I67: =ROUND(I55-I45,2) -> 0 | J67: =ROUND(J55-J45,2) -> 0 | ... O67: =ROUND(O55-O45,2) -> 0
B68: Total — variable + fixed = total overhead variance | C68: =ROUND(C33+C49-C58,2) -> 0 | D68: =ROUND(D33+D49-D58,2) -> 0 | E68: =ROUND(E33+E49-E58,2) -> 0 | F68: =ROUND(F33+F49-F58,2) -> 0 | G68: =ROUND(G33+G49-G58,2) -> 0 | H68: =ROUND(H33+H49-H58,2) -> 0 | I68: =ROUND(I33+I49-I58,2) -> 0 | J68: =ROUND(J33+J49-J58,2) -> 0 | ... O68: =ROUND(O33+O49-O58,2) -> 0
B69: Status | C69: {=IF(SUMPRODUCT(ABS(C62:C68))=0,"OK","ERROR")} -> OK | D69: {=IF(SUMPRODUCT(ABS(D62:D68))=0,"OK","ERROR")} -> OK | E69: {=IF(SUMPRODUCT(ABS(E62:E68))=0,"OK","ERROR")} -> OK | F69: {=IF(SUMPRODUCT(ABS(F62:F68))=0,"OK","ERROR")} -> OK | G69: {=IF(SUMPRODUCT(ABS(G62:G68))=0,"OK","ERROR")} -> OK | H69: {=IF(SUMPRODUCT(ABS(H62:H68))=0,"OK","ERROR")} -> OK | I69: {=IF(SUMPRODUCT(ABS(I62:I68))=0,"OK","ERROR")} -> OK | J69: {=IF(SUMPRODUCT(ABS(J62:J68))=0,"OK","ERROR")} -> OK | ... O69: {=IF(SUMPRODUCT(ABS(O62:O68))=0,"OK","ERROR")} -> OK

Sheet Dashboard
B1: Variance Dashboard
B3: Performance Summary | C3: Budget | D3: Actual + Forecast | E3: Variance | F3: F/A
B4: Total units | C4: ='Rolling Budget'!O10 -> 237000 | D4: ='Actuals & Forecast'!O10 -> 242357.88 | E4: =(D4-C4)*1 -> 5357.875 | F4: =IF(E4>0,"F","U") -> F
B5: Revenue (₹) | C5: ='Rolling Budget'!O16 -> 286500000 | D5: ='Actuals & Forecast'!O21 -> 2.9665759e+08 | E5: =(D5-C5)*1 -> 10157595 | F5: =IF(E5>0,"F","U") -> F
B6: Total variable cost (₹) | C6: ='Rolling Budget'!O24 -> 178380000 | D6: ='Actuals & Forecast'!O46 -> 1.8925596e+08 | E6: =(D6-C6)*-1 -> -10875960 | F6: =IF(E6>0,"F","U") -> U
B7: Contribution (₹) | C7: ='Rolling Budget'!O26 -> 108120000 | D7: ='Actuals & Forecast'!O48 -> 1.0740163e+08 | E7: =(D7-C7)*1 -> -718365.21 | F7: =IF(E7>0,"F","U") -> U
B8: Fixed overhead (₹) | C8: ='Rolling Budget'!O34 -> 78000000 | D8: ='Actuals & Forecast'!O40 -> 79403000 | E8: =(D8-C8)*-1 -> -1403000 | F8: =IF(E8>0,"F","U") -> U
B9: Operating profit (₹) | C9: ='Rolling Budget'!O36 -> 30120000 | D9: ='Actuals & Forecast'!O51 -> 27998635 | E9: =(D9-C9)*1 -> -2121365.2 | F9: =IF(E9>0,"F","U") -> U
B10: Operating margin % | C10: ='Rolling Budget'!O37 -> 0.10513089 | D10: ='Actuals & Forecast'!O52 -> 0.094380307 | E10: =(D10-C10)*1 -> -0.010750583 | F10: =IF(E10>0,"F","U") -> U
B12: Profit Bridge — Budget To Actual + Forecast | C12: ₹ | D12: F/U
B13: Budget operating profit | C13: ='Rolling Budget'!O36 -> 30120000
B14: Sales price variance | C14: ='Sales Variances'!O46 -> 3480057.1 | D14: =IF(C14>0,"F","U") -> F
B15: Sales volume contribution variance | C15: ='Sales Variances'!O47 -> 2508721 | D15: =IF(C15>0,"F","U") -> F
B16: Sales mix variance | C16: ='Sales Variances'!O48 -> 64444.861 | D16: =IF(C16>0,"F","U") -> F
B17: Sales quantity variance | C17: ='Sales Variances'!O49 -> 2444276.1 | D17: =IF(C17>0,"F","U") -> F
B18: Direct material variance | C18: ='Overhead Variances'!O16 -> -3951076.8 | D18: =IF(C18>0,"F","U") -> U
B19: Direct labour rate variance | C19: ='Overhead Variances'!O22 -> -728855.68 | D19: =IF(C19>0,"F","U") -> U
B20: Direct labour efficiency variance | C20: ='Overhead Variances'!O23 -> -1061283.6 | D20: =IF(C20>0,"F","U") -> U
B21: Variable overhead expenditure variance | C21: ='Overhead Variances'!O31 -> -510005.08 | D21: =IF(C21>0,"F","U") -> U
B22: Variable overhead efficiency variance | C22: ='Overhead Variances'!O32 -> -455922.12 | D22: =IF(C22>0,"F","U") -> U
B23: Fixed overhead expenditure variance | C23: ='Overhead Variances'!O45 -> -1403000 | D23: =IF(C23>0,"F","U") -> U
B24: Actual + forecast operating profit | C24: =C13+C14+C15+C18+C19+C20+C21+C22+C23 -> 27998635
B25: Check — bridge vs reported profit (nil) | C25: =ROUND(C24-'Actuals & Forecast'!O51,0) -> 0
B27: Absorption Memorandum | C27: ₹ | D27: F/A
B28: Fixed overhead absorbed at standard rate | C28: ='Overhead Variances'!O44 -> 79820886
B29: Budgeted fixed overhead | C29: ='Overhead Variances'!O42 -> 78000000
B30: Fixed overhead volume variance | C30: ='Overhead Variances'!O46 -> 1820886.4 | D30: =IF(C30>0,"F","U") -> F
B31: Capacity variance | C31: ='Overhead Variances'!O47 -> 3547864.1 | D31: =IF(C31>0,"F","U") -> F
B32: Efficiency variance | C32: ='Overhead Variances'!O48 -> -1726977.7 | D32: =IF(C32>0,"F","U") -> U
B34: Commentary
B35: Operating profit of ₹2,79,98,726 is ₹21,21,274 below the rolling budget of ₹3,01,20,000 (7.0%).
B36: Sales performance is favourable at ₹59,88,879: price ₹34,80,061 F and volume ₹25,08,818 F, of which mix ₹64,485 F and quantity ₹24,44,333 F.
B37: Direct costs are unfavorable by ₹57,41,225, material ₹39,51,083 U, labour rate ₹7,28,858 U, labour efficiency ₹10,61,284 U.
B38: Overheads are unfavorable by ₹5,47,974: variable OH spending ₹5,10,006 U, variable OH efficiency ₹4,55,922 U, fixed OH expenditure ₹14,03,000 U.
B39: Fixed overhead volume variance of ₹18,20,955 F reflects higher hours worked than budget (capacity ₹35,47,934 F) offset by labour efficiency ₹17,26,979 U.
B40: Largest single driver: Direct material variance at ₹39,51,083 unfavorable .
B42: Monthly operating profit (₹) | C42: =DATE(2026,4,1) -> 46113 | D42: =EDATE(C42,1) -> 46143 | E42: =EDATE(D42,1) -> 46174 | F42: =EDATE(E42,1) -> 46204 | G42: =EDATE(F42,1) -> 46235 | H42: =EDATE(G42,1) -> 46266 | I42: =EDATE(H42,1) -> 46296 | J42: =EDATE(I42,1) -> 46327 | K42: =EDATE(J42,1) -> 46357 | ... N42: =EDATE(M42,1) -> 46447
B43: Budget | C43: ='Rolling Budget'!C36 -> 1609000 | D43: ='Rolling Budget'!D36 -> 2059500 | E43: ='Rolling Budget'!E36 -> 2510000 | F43: ='Rolling Budget'!F36 -> 2960500 | G43: ='Rolling Budget'!G36 -> 3411000 | H43: ='Rolling Budget'!H36 -> 2960500 | I43: ='Rolling Budget'!I36 -> 2059500 | J43: ='Rolling Budget'!J36 -> 1609000 | ... N43: ='Rolling Budget'!N36 -> 2510000
B44: Actual / Forecast | C44: ='Actuals & Forecast'!C51 -> 1848002 | D44: ='Actuals & Forecast'!D51 -> 2373596 | E44: ='Actuals & Forecast'!E51 -> 1929632 | F44: ='Actuals & Forecast'!F51 -> 3054609 | G44: ='Actuals & Forecast'!G51 -> 3794048 | H44: ='Actuals & Forecast'!H51 -> 2950729 | I44: ='Actuals & Forecast'!I51 -> 1643696.3 | J44: ='Actuals & Forecast'!J51 -> 1206528.1 | ... N44: ='Actuals & Forecast'!N51 -> 2080864.5
B45: Variance | C45: =C44-C43 -> 239002 | D45: =D44-D43 -> 314096 | E45: =E44-E43 -> -580368 | F45: =F44-F43 -> 94109 | G45: =G44-G43 -> 383048 | H45: =H44-H43 -> -9771 | I45: =I44-I43 -> -415803.72 | J45: =J44-J43 -> -402471.95 | ... N45: =N44-N43 -> -429135.5
B47: Variance driver (₹)
B48: Sales price | C48: =C14 -> 3480057.1
B49: Sales volume | C49: =C15 -> 2508721
B50: Direct material | C50: =C18 -> -3951076.8
B51: Labour rate | C51: =C19 -> -728855.68
B52: Labour efficiency | C52: =C20 -> -1061283.6
B53: Variable OH spending | C53: =C21 -> -510005.08
B54: Variable OH efficiency | C54: =C22 -> -455922.12
B55: Fixed OH expenditure | C55: =C23 -> -1403000
B56: Overhead Variances — all reconciliations nil (FY) | C56: ='Overhead Variances'!O69 -> OK
B57: Overhead Variances — all reconciliations nil (every month) | C57: =IF(COUNTIF('Overhead Variances'!C69:N69,"ERROR")=0,"OK","ERROR") -> OK
B58: Sales Variances — all reconciliations nil (every month) | C58: =IF(COUNTIF('Sales Variances'!C59:N59,"ERROR")=0,"OK","ERROR") -> OK
B59: Overall Model Status | C59: =IF(COUNTIF(C56:C58,"ERROR")=0,"ALL CHECKS PASS",COUNTIF(C56:C58,"ERROR")&" CHECKS FAILED") -> ALL CHECKS PASS
